{"conclusion":"success","createdAt":"2026-05-09T20:10:42Z","databaseId":25610684871,"displayTitle":"Merge pull request #16 from Svetozar-Technologies/issue-15-3b7dcdf82f3e","event":"push","headSha":"cbede2404d1c5d7a4099ccb16cb4713ceab068c6","jobs":[{"completedAt":"2026-05-09T22:02:33Z","conclusion":"success","databaseId":75180219198,"name":"Refresh Official Sources","startedAt":"2026-05-09T20:10:46Z","status":"completed","steps":[{"completedAt":"2026-05-09T20:10:50Z","conclusion":"success","name":"Set up job","number":1,"startedAt":"2026-05-09T20:10:47Z","status":"completed"},{"completedAt":"2026-05-09T20:10:55Z","conclusion":"success","name":"Checkout","number":2,"startedAt":"2026-05-09T20:10:50Z","status":"completed"},{"completedAt":"2026-05-09T20:10:57Z","conclusion":"success","name":"Setup Node","number":3,"startedAt":"2026-05-09T20:10:55Z","status":"completed"},{"completedAt":"2026-05-09T20:11:00Z","conclusion":"success","name":"Install","number":4,"startedAt":"2026-05-09T20:10:57Z","status":"completed"},{"completedAt":"2026-05-09T20:11:18Z","conclusion":"success","name":"Discover Central Acts","number":5,"startedAt":"2026-05-09T20:11:00Z","status":"completed"},{"completedAt":"2026-05-09T20:12:17Z","conclusion":"success","name":"Discover Regional Language Sources","number":6,"startedAt":"2026-05-09T20:11:18Z","status":"completed"},{"completedAt":"2026-05-09T20:12:17Z","conclusion":"success","name":"Configure commit author","number":7,"startedAt":"2026-05-09T20:12:17Z","status":"completed"},{"completedAt":"2026-05-09T22:02:23Z","conclusion":"success","name":"Build Pages with resumable checkpoints","number":8,"startedAt":"2026-05-09T20:12:17Z","status":"completed"},{"completedAt":"2026-05-09T22:02:23Z","conclusion":"success","name":"Configure GitHub Pages","number":9,"startedAt":"2026-05-09T22:02:23Z","status":"completed"},{"completedAt":"2026-05-09T22:02:25Z","conclusion":"success","name":"Upload GitHub Pages artifact","number":10,"startedAt":"2026-05-09T22:02:23Z","status":"completed"},{"completedAt":"2026-05-09T22:02:31Z","conclusion":"success","name":"Deploy to GitHub Pages","number":11,"startedAt":"2026-05-09T22:02:25Z","status":"completed"},{"completedAt":"2026-05-09T22:02:31Z","conclusion":"success","name":"Post Setup Node","number":21,"startedAt":"2026-05-09T22:02:31Z","status":"completed"},{"completedAt":"2026-05-09T22:02:31Z","conclusion":"success","name":"Post Checkout","number":22,"startedAt":"2026-05-09T22:02:31Z","status":"completed"},{"completedAt":"2026-05-09T22:02:31Z","conclusion":"success","name":"Complete job","number":23,"startedAt":"2026-05-09T22:02:31Z","status":"completed"}],"url":"https://github.com/Svetozar-Technologies/indian-law/actions/runs/25610684871/job/75180219198"}],"url":"https://github.com/Svetozar-Technologies/indian-law/actions/runs/25610684871","workflowName":"Refresh Laws and Deploy Pages"}
