{
  "cacheVersion": 1,
  "fetchedAt": "2026-05-08T21:17:20.428Z",
  "sourceUrl": "https://www.indiacode.nic.in/handle/123456789/1938",
  "completeFetch": true,
  "maxSections": null,
  "law": {
    "slug": "the-national-council-for-teacher-education-act-1993",
    "handle": "1938",
    "collectionHandle": "123456789/1362",
    "title": "The National Council for Teacher Education Act, 1993",
    "actNumber": "73",
    "enactmentDate": "1993-12-29",
    "sourceUrl": "https://www.indiacode.nic.in/handle/123456789/1938",
    "sources": {
      "en": [
        {
          "kind": "html",
          "url": "https://www.indiacode.nic.in/handle/123456789/1938"
        },
        {
          "kind": "pdf",
          "url": "https://www.indiacode.nic.in/bitstream/123456789/1938/1/AAAA1993____73.pdf",
          "title": "The National Council for Teacher Education Act, 1993"
        },
        {
          "kind": "pdf",
          "url": "https://www.indiacode.nic.in/ViewFileUploaded?path=AC_CEN_9_67_00001_199373_1517807322617/rulesindividualfile/&file=5+compiled+list.pdf",
          "title": ""
        },
        {
          "kind": "pdf",
          "url": "https://www.indiacode.nic.in/ViewFileUploaded?path=AC_CEN_9_67_00001_199373_1517807322617/rulesindividualfile/&file=40+compiled+list.pdf",
          "title": ""
        },
        {
          "kind": "pdf",
          "url": "https://www.indiacode.nic.in/ViewFileUploaded?path=AC_CEN_9_67_00001_199373_1517807322617/rulesindividualfile/&file=NCTE+Amemdnent+rules+2003+sl+06.pdf",
          "title": ""
        },
        {
          "kind": "pdf",
          "url": "https://www.indiacode.nic.in/ViewFileUploaded?path=AC_CEN_9_67_00001_199373_1517807322617/rulesindividualfile/&file=NCTE+Amemdnent+rules+2003+sl+07.pdf",
          "title": ""
        },
        {
          "kind": "pdf",
          "url": "https://www.indiacode.nic.in/ViewFileUploaded?path=AC_CEN_9_67_00001_199373_1517807322617/rulesindividualfile/&file=annual+statement+of+account+rules+2007.pdf",
          "title": ""
        },
        {
          "kind": "pdf",
          "url": "https://www.indiacode.nic.in/ViewFileUploaded?path=AC_CEN_9_67_00001_199373_1517807322617/rulesindividualfile/&file=NCTE+Amemdnent+rules+2011+SL+08.pdf",
          "title": ""
        },
        {
          "kind": "pdf",
          "url": "https://www.indiacode.nic.in/ViewFileUploaded?path=AC_CEN_9_67_00001_199373_1517807322617/rulesindividualfile/&file=NCTE+Amemdnent+rules+2015+sl+no.+12.pdf",
          "title": ""
        },
        {
          "kind": "pdf",
          "url": "https://www.indiacode.nic.in/ViewFileUploaded?path=AC_CEN_9_67_00001_199373_1517807322617/rulesindividualfile/&file=NCTE+appointment+of+CP.pdf",
          "title": ""
        },
        {
          "kind": "pdf",
          "url": "https://www.indiacode.nic.in/ViewFileUploaded?path=AC_CEN_9_67_00001_199373_1517807322617/rulesindividualfile/&file=NCTE+RULES+VCP+APPOINTMENT+2012+sl+09.pdf",
          "title": ""
        },
        {
          "kind": "pdf",
          "url": "https://www.indiacode.nic.in/ViewFileUploaded?path=AC_CEN_9_67_00001_199373_1517807322617/rulesindividualfile/&file=NCTE+Appointment+of+CP+amendment.pdf",
          "title": ""
        },
        {
          "kind": "pdf",
          "url": "https://www.indiacode.nic.in/ViewFileUploaded?path=AC_CEN_9_67_00001_199373_1517807322617/regulationindividualfile/&file=30-12-1993.pdf",
          "title": ""
        },
        {
          "kind": "pdf",
          "url": "https://www.indiacode.nic.in/ViewFileUploaded?path=AC_CEN_9_67_00001_199373_1517807322617/regulationindividualfile/&file=10-07-1995.pdf",
          "title": ""
        },
        {
          "kind": "pdf",
          "url": "https://www.indiacode.nic.in/ViewFileUploaded?path=AC_CEN_9_67_00001_199373_1517807322617/regulationindividualfile/&file=06-01-1996.pdf",
          "title": ""
        },
        {
          "kind": "pdf",
          "url": "https://www.indiacode.nic.in/ViewFileUploaded?path=AC_CEN_9_67_00001_199373_1517807322617/regulationindividualfile/&file=22-01-1996.pdf",
          "title": ""
        },
        {
          "kind": "pdf",
          "url": "https://www.indiacode.nic.in/ViewFileUploaded?path=AC_CEN_9_67_00001_199373_1517807322617/regulationindividualfile/&file=24-02-1996.pdf",
          "title": ""
        },
        {
          "kind": "pdf",
          "url": "https://www.indiacode.nic.in/ViewFileUploaded?path=AC_CEN_9_67_00001_199373_1517807322617/regulationindividualfile/&file=17+compiled+list.pdf",
          "title": ""
        },
        {
          "kind": "pdf",
          "url": "https://www.indiacode.nic.in/ViewFileUploaded?path=AC_CEN_9_67_00001_199373_1517807322617/regulationindividualfile/&file=19+compiled+list.pdf",
          "title": ""
        },
        {
          "kind": "pdf",
          "url": "https://www.indiacode.nic.in/ViewFileUploaded?path=AC_CEN_9_67_00001_199373_1517807322617/regulationindividualfile/&file=06-07-1996.pdf",
          "title": ""
        },
        {
          "kind": "pdf",
          "url": "https://www.indiacode.nic.in/ViewFileUploaded?path=AC_CEN_9_67_00001_199373_1517807322617/regulationindividualfile/&file=05-04-1997_%282%29.pdf",
          "title": ""
        },
        {
          "kind": "pdf",
          "url": "https://www.indiacode.nic.in/ViewFileUploaded?path=AC_CEN_9_67_00001_199373_1517807322617/regulationindividualfile/&file=05-04-1997.pdf",
          "title": ""
        },
        {
          "kind": "pdf",
          "url": "https://www.indiacode.nic.in/ViewFileUploaded?path=AC_CEN_9_67_00001_199373_1517807322617/regulationindividualfile/&file=21+compiled+list.pdf",
          "title": ""
        },
        {
          "kind": "pdf",
          "url": "https://www.indiacode.nic.in/ViewFileUploaded?path=AC_CEN_9_67_00001_199373_1517807322617/regulationindividualfile/&file=19-07-1997.pdf",
          "title": ""
        },
        {
          "kind": "pdf",
          "url": "https://www.indiacode.nic.in/ViewFileUploaded?path=AC_CEN_9_67_00001_199373_1517807322617/regulationindividualfile/&file=13-02-1999.pdf",
          "title": ""
        },
        {
          "kind": "pdf",
          "url": "https://www.indiacode.nic.in/ViewFileUploaded?path=AC_CEN_9_67_00001_199373_1517807322617/regulationindividualfile/&file=20-03-1999.pdf",
          "title": ""
        },
        {
          "kind": "pdf",
          "url": "https://www.indiacode.nic.in/ViewFileUploaded?path=AC_CEN_9_67_00001_199373_1517807322617/regulationindividualfile/&file=27-03-1999.pdf",
          "title": ""
        },
        {
          "kind": "pdf",
          "url": "https://www.indiacode.nic.in/ViewFileUploaded?path=AC_CEN_9_67_00001_199373_1517807322617/regulationindividualfile/&file=28-10-2000.pdf",
          "title": ""
        },
        {
          "kind": "pdf",
          "url": "https://www.indiacode.nic.in/ViewFileUploaded?path=AC_CEN_9_67_00001_199373_1517807322617/regulationindividualfile/&file=16-12-2000.pdf",
          "title": ""
        },
        {
          "kind": "pdf",
          "url": "https://www.indiacode.nic.in/ViewFileUploaded?path=AC_CEN_9_67_00001_199373_1517807322617/regulationindividualfile/&file=05-07-2008.pdf",
          "title": ""
        },
        {
          "kind": "pdf",
          "url": "https://www.indiacode.nic.in/ViewFileUploaded?path=AC_CEN_9_67_00001_199373_1517807322617/regulationindividualfile/&file=11-08-2001.pdf",
          "title": ""
        },
        {
          "kind": "pdf",
          "url": "https://www.indiacode.nic.in/ViewFileUploaded?path=AC_CEN_9_67_00001_199373_1517807322617/regulationindividualfile/&file=04-09-2001.pdf",
          "title": ""
        },
        {
          "kind": "pdf",
          "url": "https://www.indiacode.nic.in/ViewFileUploaded?path=AC_CEN_9_67_00001_199373_1517807322617/regulationindividualfile/&file=04-09-2001_-2.pdf",
          "title": ""
        },
        {
          "kind": "pdf",
          "url": "https://www.indiacode.nic.in/ViewFileUploaded?path=AC_CEN_9_67_00001_199373_1517807322617/regulationindividualfile/&file=05-10-2001.pdf",
          "title": ""
        },
        {
          "kind": "pdf",
          "url": "https://www.indiacode.nic.in/ViewFileUploaded?path=AC_CEN_9_67_00001_199373_1517807322617/regulationindividualfile/&file=26-11-2001.pdf",
          "title": ""
        },
        {
          "kind": "pdf",
          "url": "https://www.indiacode.nic.in/ViewFileUploaded?path=AC_CEN_9_67_00001_199373_1517807322617/regulationindividualfile/&file=08-12-2001.pdf",
          "title": ""
        },
        {
          "kind": "pdf",
          "url": "https://www.indiacode.nic.in/ViewFileUploaded?path=AC_CEN_9_67_00001_199373_1517807322617/regulationindividualfile/&file=NCTE+RC+procedure+amendment+sl+22.pdf",
          "title": ""
        },
        {
          "kind": "pdf",
          "url": "https://www.indiacode.nic.in/ViewFileUploaded?path=AC_CEN_9_67_00001_199373_1517807322617/regulationindividualfile/&file=32+compiled+list.pdf",
          "title": ""
        },
        {
          "kind": "pdf",
          "url": "https://www.indiacode.nic.in/ViewFileUploaded?path=AC_CEN_9_67_00001_199373_1517807322617/regulationindividualfile/&file=13-11-2002.pdf",
          "title": ""
        },
        {
          "kind": "pdf",
          "url": "https://www.indiacode.nic.in/ViewFileUploaded?path=AC_CEN_9_67_00001_199373_1517807322617/regulationindividualfile/&file=34+compiled+list.pdf",
          "title": ""
        },
        {
          "kind": "pdf",
          "url": "https://www.indiacode.nic.in/ViewFileUploaded?path=AC_CEN_9_67_00001_199373_1517807322617/regulationindividualfile/&file=rr+regulation+part1.pdf",
          "title": ""
        },
        {
          "kind": "pdf",
          "url": "https://www.indiacode.nic.in/ViewFileUploaded?path=AC_CEN_9_67_00001_199373_1517807322617/regulationindividualfile/&file=NCTE+CPF+rules+sl+39.pdf",
          "title": ""
        },
        {
          "kind": "pdf",
          "url": "https://www.indiacode.nic.in/ViewFileUploaded?path=AC_CEN_9_67_00001_199373_1517807322617/regulationindividualfile/&file=29-08-2003.pdf",
          "title": ""
        },
        {
          "kind": "pdf",
          "url": "https://www.indiacode.nic.in/ViewFileUploaded?path=AC_CEN_9_67_00001_199373_1517807322617/regulationindividualfile/&file=17-09-2003.pdf",
          "title": ""
        },
        {
          "kind": "pdf",
          "url": "https://www.indiacode.nic.in/ViewFileUploaded?path=AC_CEN_9_67_00001_199373_1517807322617/regulationindividualfile/&file=09-10-2003.pdf",
          "title": ""
        },
        {
          "kind": "pdf",
          "url": "https://www.indiacode.nic.in/ViewFileUploaded?path=AC_CEN_9_67_00001_199373_1517807322617/regulationindividualfile/&file=05-01-2004.pdf",
          "title": ""
        },
        {
          "kind": "pdf",
          "url": "https://www.indiacode.nic.in/ViewFileUploaded?path=AC_CEN_9_67_00001_199373_1517807322617/regulationindividualfile/&file=39+compiled+list.pdf",
          "title": ""
        },
        {
          "kind": "pdf",
          "url": "https://www.indiacode.nic.in/ViewFileUploaded?path=AC_CEN_9_67_00001_199373_1517807322617/regulationindividualfile/&file=01-12-2005.pdf",
          "title": ""
        },
        {
          "kind": "pdf",
          "url": "https://www.indiacode.nic.in/ViewFileUploaded?path=AC_CEN_9_67_00001_199373_1517807322617/regulationindividualfile/&file=13-01-2006.pdf",
          "title": ""
        },
        {
          "kind": "pdf",
          "url": "https://www.indiacode.nic.in/ViewFileUploaded?path=AC_CEN_9_67_00001_199373_1517807322617/regulationindividualfile/&file=25-01-2006.pdf",
          "title": ""
        },
        {
          "kind": "pdf",
          "url": "https://www.indiacode.nic.in/ViewFileUploaded?path=AC_CEN_9_67_00001_199373_1517807322617/regulationindividualfile/&file=21-07-2006.pdf",
          "title": ""
        },
        {
          "kind": "pdf",
          "url": "https://www.indiacode.nic.in/ViewFileUploaded?path=AC_CEN_9_67_00001_199373_1517807322617/regulationindividualfile/&file=15-11-2006.pdf",
          "title": ""
        },
        {
          "kind": "pdf",
          "url": "https://www.indiacode.nic.in/ViewFileUploaded?path=AC_CEN_9_67_00001_199373_1517807322617/regulationindividualfile/&file=02-01-2007.pdf",
          "title": ""
        },
        {
          "kind": "pdf",
          "url": "https://www.indiacode.nic.in/ViewFileUploaded?path=AC_CEN_9_67_00001_199373_1517807322617/regulationindividualfile/&file=Executive+Committee+regulations+sl+18.pdf",
          "title": ""
        },
        {
          "kind": "pdf",
          "url": "https://www.indiacode.nic.in/ViewFileUploaded?path=AC_CEN_9_67_00001_199373_1517807322617/regulationindividualfile/&file=10-12-2007.pdf",
          "title": ""
        },
        {
          "kind": "pdf",
          "url": "https://www.indiacode.nic.in/ViewFileUploaded?path=AC_CEN_9_67_00001_199373_1517807322617/regulationindividualfile/&file=31-01-2008.pdf",
          "title": ""
        },
        {
          "kind": "pdf",
          "url": "https://www.indiacode.nic.in/ViewFileUploaded?path=AC_CEN_9_67_00001_199373_1517807322617/regulationindividualfile/&file=31-01-2008_%282%29.pdf",
          "title": ""
        },
        {
          "kind": "pdf",
          "url": "https://www.indiacode.nic.in/ViewFileUploaded?path=AC_CEN_9_67_00001_199373_1517807322617/regulationindividualfile/&file=ncte+stenographer+c+amendment+sl+37.pdf",
          "title": ""
        },
        {
          "kind": "pdf",
          "url": "https://www.indiacode.nic.in/ViewFileUploaded?path=AC_CEN_9_67_00001_199373_1517807322617/regulationindividualfile/&file=21-07-2008.pdf",
          "title": ""
        },
        {
          "kind": "pdf",
          "url": "https://www.indiacode.nic.in/ViewFileUploaded?path=AC_CEN_9_67_00001_199373_1517807322617/regulationindividualfile/&file=22-10-2008.pdf",
          "title": ""
        },
        {
          "kind": "pdf",
          "url": "https://www.indiacode.nic.in/ViewFileUploaded?path=AC_CEN_9_67_00001_199373_1517807322617/regulationindividualfile/&file=23-05-2009.pdf",
          "title": ""
        },
        {
          "kind": "pdf",
          "url": "https://www.indiacode.nic.in/ViewFileUploaded?path=AC_CEN_9_67_00001_199373_1517807322617/regulationindividualfile/&file=ncte+rr+amendment+sl+38.pdf",
          "title": ""
        },
        {
          "kind": "pdf",
          "url": "https://www.indiacode.nic.in/ViewFileUploaded?path=AC_CEN_9_67_00001_199373_1517807322617/regulationindividualfile/&file=30-07-2009.pdf",
          "title": ""
        },
        {
          "kind": "pdf",
          "url": "https://www.indiacode.nic.in/ViewFileUploaded?path=AC_CEN_9_67_00001_199373_1517807322617/regulationindividualfile/&file=regulationse-2009-31.8.09.pdf",
          "title": ""
        },
        {
          "kind": "pdf",
          "url": "https://www.indiacode.nic.in/ViewFileUploaded?path=AC_CEN_9_67_00001_199373_1517807322617/regulationindividualfile/&file=01-04-2010.pdf",
          "title": ""
        },
        {
          "kind": "pdf",
          "url": "https://www.indiacode.nic.in/ViewFileUploaded?path=AC_CEN_9_67_00001_199373_1517807322617/regulationindividualfile/&file=26-07-2010.pdf",
          "title": ""
        },
        {
          "kind": "pdf",
          "url": "https://www.indiacode.nic.in/ViewFileUploaded?path=AC_CEN_9_67_00001_199373_1517807322617/regulationindividualfile/&file=Minimum-Qualification-2010.pdf",
          "title": ""
        },
        {
          "kind": "pdf",
          "url": "https://www.indiacode.nic.in/ViewFileUploaded?path=AC_CEN_9_67_00001_199373_1517807322617/regulationindividualfile/&file=NCTE+Guidelines+for+Tutition+fees+2010.pdf",
          "title": ""
        },
        {
          "kind": "pdf",
          "url": "https://www.indiacode.nic.in/ViewFileUploaded?path=AC_CEN_9_67_00001_199373_1517807322617/regulationindividualfile/&file=minimum-qualification-25.8.2010.pdf",
          "title": ""
        },
        {
          "kind": "pdf",
          "url": "https://www.indiacode.nic.in/ViewFileUploaded?path=AC_CEN_9_67_00001_199373_1517807322617/regulationindividualfile/&file=26-11-2010.pdf",
          "title": ""
        },
        {
          "kind": "pdf",
          "url": "https://www.indiacode.nic.in/ViewFileUploaded?path=AC_CEN_9_67_00001_199373_1517807322617/regulationindividualfile/&file=NCTE+RC+member+nomination+sl+23.pdf",
          "title": ""
        },
        {
          "kind": "pdf",
          "url": "https://www.indiacode.nic.in/ViewFileUploaded?path=AC_CEN_9_67_00001_199373_1517807322617/regulationindividualfile/&file=2-8-07-2011.pdf",
          "title": ""
        },
        {
          "kind": "pdf",
          "url": "https://www.indiacode.nic.in/ViewFileUploaded?path=AC_CEN_9_67_00001_199373_1517807322617/regulationindividualfile/&file=Minimum-Qualification-2011.pdf",
          "title": ""
        },
        {
          "kind": "pdf",
          "url": "https://www.indiacode.nic.in/ViewFileUploaded?path=AC_CEN_9_67_00001_199373_1517807322617/regulationindividualfile/&file=minimum-qualification-2.8.2011.pdf",
          "title": ""
        },
        {
          "kind": "pdf",
          "url": "https://www.indiacode.nic.in/ViewFileUploaded?path=AC_CEN_9_67_00001_199373_1517807322617/regulationindividualfile/&file=13-10-2011_searchable.pdf",
          "title": ""
        },
        {
          "kind": "pdf",
          "url": "https://www.indiacode.nic.in/ViewFileUploaded?path=AC_CEN_9_67_00001_199373_1517807322617/regulationindividualfile/&file=Minimum+Qualification_2015.pdf",
          "title": ""
        },
        {
          "kind": "pdf",
          "url": "https://www.indiacode.nic.in/ViewFileUploaded?path=AC_CEN_9_67_00001_199373_1517807322617/regulationindividualfile/&file=Regulation_2014%28Hindi+%26+English%29.pdf",
          "title": ""
        },
        {
          "kind": "pdf",
          "url": "https://www.indiacode.nic.in/ViewFileUploaded?path=AC_CEN_9_67_00001_199373_1517807322617/regulationindividualfile/&file=gazette_notification_12.11.14_searchabe.pdf",
          "title": ""
        },
        {
          "kind": "pdf",
          "url": "https://www.indiacode.nic.in/ViewFileUploaded?path=AC_CEN_9_67_00001_199373_1517807322617/regulationindividualfile/&file=ncte_gazette_dated_29.4.2017_searchable.pdf",
          "title": ""
        },
        {
          "kind": "pdf",
          "url": "https://www.indiacode.nic.in/ViewFileUploaded?path=AC_CEN_9_67_00001_199373_1517807322617/regulationindividualfile/&file=Notification9.6.2017.pdf",
          "title": ""
        },
        {
          "kind": "pdf",
          "url": "https://www.indiacode.nic.in/ViewFileUploaded?path=AC_CEN_9_67_00001_199373_1517807322617/regulationindividualfile/&file=ShiftingofRCstoNewDelhi.pdf",
          "title": ""
        },
        {
          "kind": "pdf",
          "url": "https://www.indiacode.nic.in/ViewFileUploaded?path=AC_CEN_9_67_00001_199373_1517807322617/regulationindividualfile/&file=notification9.6.2017.pdf",
          "title": ""
        },
        {
          "kind": "pdf",
          "url": "https://www.indiacode.nic.in/ViewFileUploaded?path=AC_CEN_9_67_00001_199373_1517807322617/regulationindividualfile/&file=Gazette_notification.pdf",
          "title": ""
        },
        {
          "kind": "pdf",
          "url": "https://www.indiacode.nic.in/ViewFileUploaded?path=AC_CEN_9_67_00001_199373_1517807322617/regulationindividualfile/&file=gazette_notification_28.6.18.pdf",
          "title": ""
        },
        {
          "kind": "pdf",
          "url": "https://www.indiacode.nic.in/ViewFileUploaded?path=AC_CEN_9_67_00001_199373_1517807322617/regulationindividualfile/&file=itep_2019.pdf",
          "title": ""
        },
        {
          "kind": "pdf",
          "url": "https://www.indiacode.nic.in/ViewFileUploaded?path=AC_CEN_9_67_00001_199373_1517807322617/regulationindividualfile/&file=regulations_for_integrated_teacher_education_programme_%28itep%29%281%29.pdf",
          "title": ""
        },
        {
          "kind": "pdf",
          "url": "https://www.indiacode.nic.in/ViewFileUploaded?path=AC_CEN_9_67_00001_199373_1517807322617/regulationindividualfile/&file=ncte_act_2019_searchable.pdf",
          "title": ""
        },
        {
          "kind": "pdf",
          "url": "https://www.indiacode.nic.in/ViewFileUploaded?path=AC_CEN_9_67_00001_199373_1517807322617/regulationindividualfile/&file=gazette_notification_of_ncte_regulations_%28itep%29.pdf",
          "title": ""
        },
        {
          "kind": "pdf",
          "url": "https://www.indiacode.nic.in/ViewFileUploaded?path=AC_CEN_9_67_00001_199373_1517807322617/circularindividualfile/&file=NCTE+Guidelines+for+TET.pdf",
          "title": ""
        },
        {
          "kind": "pdf",
          "url": "https://www.indiacode.nic.in/ViewFileUploaded?path=AC_CEN_9_67_00001_199373_1517807322617/circularindividualfile/&file=42A.pdf",
          "title": ""
        },
        {
          "kind": "pdf",
          "url": "https://www.indiacode.nic.in/ViewFileUploaded?path=AC_CEN_9_67_00001_199373_1517807322617/notificationindividualfile/&file=QUORUM+GAZETTE.pdf",
          "title": ""
        },
        {
          "kind": "pdf",
          "url": "https://www.indiacode.nic.in/ViewFileUploaded?path=AC_CEN_9_67_00001_199373_1517807322617/notificationindividualfile/&file=25+compiled+list.pdf",
          "title": ""
        },
        {
          "kind": "pdf",
          "url": "https://www.indiacode.nic.in/ViewFileUploaded?path=AC_CEN_9_67_00001_199373_1517807322617/notificationindividualfile/&file=14+compiled+list.pdf",
          "title": ""
        },
        {
          "kind": "pdf",
          "url": "https://www.indiacode.nic.in/ViewFileUploaded?path=AC_CEN_9_67_00001_199373_1517807322617/notificationindividualfile/&file=15+compiled+list.pdf",
          "title": ""
        },
        {
          "kind": "pdf",
          "url": "https://www.indiacode.nic.in/ViewFileUploaded?path=AC_CEN_9_67_00001_199373_1517807322617/notificationindividualfile/&file=16+compiled+list.pdf",
          "title": ""
        },
        {
          "kind": "pdf",
          "url": "https://www.indiacode.nic.in/ViewFileUploaded?path=AC_CEN_9_67_00001_199373_1517807322617/notificationindividualfile/&file=notification21_nov_19.pdf",
          "title": ""
        },
        {
          "kind": "pdf",
          "url": "https://www.indiacode.nic.in/help/userGuide.pdf",
          "title": "User Guide"
        }
      ],
      "hi": [
        {
          "kind": "pdf",
          "url": "https://www.indiacode.nic.in/bitstream/123456789/1938/2/H1993-73.pdf",
          "title": "राष्ट्री य अध्यापक शिक्षा परिषद्अधिनियम, 1993"
        }
      ]
    },
    "sections": [
      {
        "sectionId": "25571",
        "sectionNo": "1",
        "orderNo": 1,
        "title": "Short title, extent and commencement.",
        "content": "(1) This Act may be called the National Council for\nTeacher Education Act, 1993.\n\n(2) It extends to the whole of India ^1***.\n\n(3) It shall come into force on such date^2 as the Central Government may, by notification in the\nOfficial Gazette, appoint.\n\n^3[(4) Save as otherwise provided in this Act, the provisions of this Act shall apply to--\n\n(a) institutions;\n\n(b) students and teachers of the institutions;\n\n(c) schools imparting pre-primary, primary, upper primary, secondary or senior secondary\neducation and colleges providing senior secondary or intermediate education irrespective of the fact,\nby whatever names they may be called; and\n\n(d) teachers for schools and colleges referred to in clause (c).]",
        "footnotes": "1. The words \"except the State of Jammu and Kashmir\" omitted by Act 34 of 2019, s. 95 and the Fifth Schedule (w.e.f. 31-10-\n2019).\n\n2. 1st July, 1995, vide notification No. S.O. 620(E), dated 1st July, 1995, see Gazette of India, Extraordinary, Part II, sec. 3(ii).\n\n3. Ins. by Act 18 of 2011, s. 3 (w.e.f. 1-6-2012).",
        "query": "abv=CEN&statehandle=123456789/1362&actid=AC_CEN_9_67_00001_199373_1517807322617&sectionId=25571&sectionno=1&orderno=1&orgactid=AC_CEN_9_67_00001_199373_1517807322617"
      },
      {
        "sectionId": "25572",
        "sectionNo": "2",
        "orderNo": 2,
        "title": "Definitions.",
        "content": "In this Act, unless the context otherwise requires,--\n\n(a) \"appointed day\" means the date of establishment of the National Council for Teacher\nEducation under sub-section (1) of section 3;\n\n(b) \"Chairperson\" means the Chairperson of the Council appointed under clause (a) of\nsub-section (4) of section 3;\n\n(c) \"Council\" means the National Council for Teacher Education established under\nsub-section (1) of section 3;\n\n(d) \"examining body\" means a University, agency or authority to which an institution is affiliated\nfor conducting examinations in teacher education qualifications;\n\n(e) \"institution\" means an institution which offers courses or training in teacher education;\n\n^1[(ea) \"local authority\" means a Municipal Corporation, Municipal Committee, Municipal\nCouncil, Zila Parishad, District Board or Nagar Panchayat or Panchayat, or other authority (by\nwhatever name called), legally entitled to, or entrusted by the Government with the control or\nmanagement of a municipal or local fund;]\n\n(f) \"Member\" means a Member of the Council and includes the Chairperson and\nVice-Chairperson;\n\n(g) \"Member-Secretary\" means the Member-Secretary of the Council appointed under clause (c)\nof sub-section (4) of section 3;\n\n(h) \"prescribed\" means prescribed by rules made under section 31;\n\n(i) \"recognised institution\" means an institution recognised by the Council under section 14;\n\n(j) \"Regional Committee\" means a committee established under section 20;\n\n(k) \"regulations\" means regulations made under section 32;\n\n^2[(ka) \"school\" means any recognised school imparting pre-primary, primary, upper primary,\nsecondary or senior secondary education, or a college imparting senior secondary education, and\nincludes--\n\n(i) a school established, owned and controlled by the Central Government, or the State\nGovernment or a local authority;\n\n(ii) a school receiving aid or grants to meet whole or part of its expenses from the Central\nGovernment, the State Government or a local authority;\n\n(iii) a school not receiving any aid or grants to meet whole or part of its expenses from the\nCentral Government, the State Government or a local authority;]\n\n(l) \"teacher education\" means programmes of education, research or training of persons for\nequipping them to teach at pre-primary, primary, secondary and senior secondary stages in schools,\nand includes non-formal education, part-time education, adult education and correspondence\neducation;\n\n(m) \"teacher education qualification\" means a degree, diploma or certificate in teacher education\nawarded by a University or examining body in accordance with the provisions of this Act;\n\n(n) \"University\" means a University defined under clause (f) of section 2 of the University Grants\nCommission Act, 1956 (3 of 1956), and includes an institution deemed to be a University under\nsection 3 of that Act;\n\n(o) \"Vice-Chairperson\" means the Vice-Chairperson of the Council appointed under clause (b) of\nsub-section (4) of section 3.",
        "footnotes": "1 . Ins. by s. 4, ibid. (w.e.f. 1-6-2012).\n\n2 Ins. by Act 18 of 2011, s. 4 (w.e.f. 1-6-2012).",
        "query": "abv=CEN&statehandle=123456789/1362&actid=AC_CEN_9_67_00001_199373_1517807322617&sectionId=25572&sectionno=2&orderno=2&orgactid=AC_CEN_9_67_00001_199373_1517807322617"
      },
      {
        "sectionId": "25573",
        "sectionNo": "3",
        "orderNo": 3,
        "title": "Establishment of the Council.",
        "content": "(1) With effect from such date as the Central Government may,\nby notification in the Official Gazette, appoint, there shall be established a Council to be called the\nNational Council for Teacher Education.\n\n(2) The Council shall be a body corporate by the name aforesaid, having perpetual succession and a\ncommon seal with power to contract and shall, by the said name, sue and be sued.\n\n(3) The head office of the Council shall be at Delhi and the Council may, with the previous approval\nof the Central Government, establish regional offices at other places in India.\n\n(4) The Council shall consist of the following Members, namely:--\n\n(a) a Chairperson to be appointed by the Central Government;\n\n(b) a Vice-Chairperson to be appointed by the Central Government;\n\n(c) a Member-Secretary to be appointed by the Central Government;\n\n(d) the Secretary to the Government of India in the Department dealing with Education, ex officio;\n\n(e) the Chairman, University Grants Commission established under section 4 of the University\nGrants Commission Act, 1956 (3 of 1956) or a member thereof nominated by him, ex officio;\n\n(f) the Director, National Council of Educational Research and Training, ex officio;\n\n(g) the Director, National Institute of Educational Planning and Administration, ex officio;\n\n(h) the Adviser (Education), Planning Commission, ex officio;\n\n(i) the Chairman, Central Board of Secondary Education, ex officio;\n\n(j) the Financial Adviser to the Government of India in the Department dealing with\nEducation, ex officio;\n\n(k) the Member-Secretary, All-India Council for Technical Education, ex officio;\n\n(l) the Chairpersons of all Regional Committees, ex officio;\n\n(m) thirteen persons possessing experience and knowledge in the field of education or teaching to\nbe appointed by the Central Government as under, from amongst the--\n\n(i) Deans of Faculties of Education and Professors of\nEducation in Universities\n--Four;\n\n(ii) experts in secondary teacher education --One;\n\n(iii) experts in pre-primary and primary teacher education --Three;\n\n(iv) experts in non-formal education and adult education --Two;\n\n(v) experts in the field of natural sciences, social sciences,\nlinguistics, vocational education, work experience,\neducational technology and special education, by rotation,\nin the manner prescribed\n--Three;\n\n(n) nine Members to be appointed by the Central Government to represent the States and Union\nterritory Administrations in the manner prescribed;\n\n(o) three Members of Parliament of whom one shall be nominated by the Chairman of the\nCouncil of States and two by the Speaker of the House of the People;\n\n(p) three Members to be appointed by the Central Government from amongst teachers of primary\nand secondary education and teachers of recognised institutions.\n\n(5) It is hereby declared that the office of the Member of the Council shall not disqualify its holder for\nbeing chosen as or for being a member of either House of Parliament.",
        "footnotes": "",
        "query": "abv=CEN&statehandle=123456789/1362&actid=AC_CEN_9_67_00001_199373_1517807322617&sectionId=25573&sectionno=3&orderno=3&orgactid=AC_CEN_9_67_00001_199373_1517807322617"
      },
      {
        "sectionId": "25574",
        "sectionNo": "4",
        "orderNo": 4,
        "title": "Term of office and conditions of service of Members.",
        "content": "(1) The Chairperson, Vice-Chairperson\nand the Member-Secretary shall hold office on a full-time basis.\n\n(2) The term of office of the Chairperson, the Vice-Chairperson and the Member-Secretary shall be\nfour years, or till they complete the age of sixty years, whichever is earlier.\n\n(3) The conditions of service of the Chairperson, the Vice-Chairperson and the Member-Secretary\nshall be such as may be prescribed.\n\n(4) The term of office of Members other than the Members specified in clauses (a) to (l) and clauses\n(n) and (o) of sub-section (4) of section 3 shall be two years or till fresh appointments are made,\nwhichever is later, and other conditions of service of such Members shall be such as may be prescribed.\n\n(5) If a casual vacancy occurs in the office of Chairperson, whether by reason of death, resignation or\ninability to discharge the functions of a Chairperson owing to illness or other incapacity, the\nVice-Chairperson holding office as such for the time being, shall act as the Chairperson and shall, unless\nany other person is appointed earlier as Chairperson, hold office of the Chairperson for the remainder of\nthe term of office of the person in whose place the said person is to so act.\n\n(6) If a casual vacancy occurs in the office of the Vice-Chairperson or any other Member, whether by\nreason of death, resignation or inability to discharge his functions owing to illness or other incapacity, such vacancy shall be filled up by making fresh appointment and the person so appointed shall hold office\nfor the remainder of the term of the office of the person in whose place such person is so appointed.\n\n(7) The Chairperson shall, in addition to presiding over the meetings of the Council, exercise and\ndischarge such powers and duties of the Council as may be delegated to him by the Council and such\nother powers and duties as may be prescribed.\n\n(8) The Vice-Chairperson shall perform such functions as may be assigned to him by the Chairperson\nfrom time to time.",
        "footnotes": "",
        "query": "abv=CEN&statehandle=123456789/1362&actid=AC_CEN_9_67_00001_199373_1517807322617&sectionId=25574&sectionno=4&orderno=4&orgactid=AC_CEN_9_67_00001_199373_1517807322617"
      },
      {
        "sectionId": "25575",
        "sectionNo": "5",
        "orderNo": 5,
        "title": "Disqualification for office of Member.",
        "content": "A person shall be disqualified for being appointed as a\nMember if he--\n\n(a) has been convicted and sentenced to imprisonment for an offence, which, in the opinion of the\nCentral Government, involves moral turpitude; or\n\n(b) is an undischarged insolvent; or\n\n(c) is of unsound mind and stands so declared by a competent court; or\n\n(d) has been removed or dismissed from the service of the Government or a body corporate\nowned or controlled by the Government; or\n\n(e) has in the opinion of the Central Government such financial or other interest in the Council as\nis likely to affect prejudicially the discharge by him of his functions as a Member.",
        "footnotes": "",
        "query": "abv=CEN&statehandle=123456789/1362&actid=AC_CEN_9_67_00001_199373_1517807322617&sectionId=25575&sectionno=5&orderno=5&orgactid=AC_CEN_9_67_00001_199373_1517807322617"
      },
      {
        "sectionId": "25576",
        "sectionNo": "6",
        "orderNo": 6,
        "title": "Vacation of office of Member.",
        "content": "The Central Government shall remove a Member if he--\n\n(a) becomes subject to any of the disqualifications mentioned in section 5:\n\nProvided that no Member shall be removed on the ground that he has become subject to the\ndisqualification mentioned in clause (e) of that section, unless he has been given a reasonable\nopportunity of being heard in the matter; or\n\n(b) refuses to act or becomes incapable of acting; or\n\n(c) is, without obtaining leave of absence from the Council, absent from three consecutive\nmeetings of the Council; or\n\n(d) in the opinion of the Central Government, has so abused his position as to render his\ncontinuance in office detrimental to the public interest:\n\nProvided that no Member shall be removed under this clause unless he has been given a\nreasonable opportunity of being heard in the matter.",
        "footnotes": "",
        "query": "abv=CEN&statehandle=123456789/1362&actid=AC_CEN_9_67_00001_199373_1517807322617&sectionId=25576&sectionno=6&orderno=6&orgactid=AC_CEN_9_67_00001_199373_1517807322617"
      },
      {
        "sectionId": "25577",
        "sectionNo": "7",
        "orderNo": 7,
        "title": "Meetings of the Council.",
        "content": "(1) The Council shall meet at such time and places, and shall observe\nsuch rules of procedure in regard to the transaction of business at its meetings (including the quorum at\nsuch meetings) as may be provided by regulations:\n\nProvided that the Council shall meet at least once every year.\n\n(2) The Chairperson, and in the absence of the Chairperson, the Vice-Chairperson shall preside at the\nmeetings of the Council.\n\n(3) If for any reason the Chairperson and the Vice-Chairperson, both are unable to attend any meeting\nof the Council, any other Member chosen by the Members present at the meeting shall preside at that\nmeeting.\n\n(4) All questions which come up before any meeting of the Council shall be decided by a majority of\nvotes of the Members present and voting and in the event of any equality of votes, the Chairperson, or in\nthe absence of the Chairperson the person presiding, shall have and exercise a second or casting vote.",
        "footnotes": "",
        "query": "abv=CEN&statehandle=123456789/1362&actid=AC_CEN_9_67_00001_199373_1517807322617&sectionId=25577&sectionno=7&orderno=7&orgactid=AC_CEN_9_67_00001_199373_1517807322617"
      },
      {
        "sectionId": "25578",
        "sectionNo": "8",
        "orderNo": 8,
        "title": "Vacancies, etc., not to invalidate proceedings of the Council.",
        "content": "No act or proceeding of the\nCouncil shall be invalid merely by reason of--\n\n(a) any vacancy in, or any defect in the constitution of, the Council; or\n\n(b) any defect in the appointment of a person acting as a Member of the Council; or\n\n(c) any irregularity in the procedure of the Council not affecting the merits of the case.",
        "footnotes": "",
        "query": "abv=CEN&statehandle=123456789/1362&actid=AC_CEN_9_67_00001_199373_1517807322617&sectionId=25578&sectionno=8&orderno=8&orgactid=AC_CEN_9_67_00001_199373_1517807322617"
      },
      {
        "sectionId": "25579",
        "sectionNo": "9",
        "orderNo": 9,
        "title": "Power to co-opt.",
        "content": "(1) The Council may co-opt, in such manner and for such purposes as may be\ndetermined by regulations, not more than three persons, whose assistance or advice it may desire in\ncarrying out any of the provisions of this Act.\n\n(2) The person co-opted by the Council under sub-section (1) for any purpose shall have a right to\ntake part in the discussions relevant to that purpose, but shall not have a right to vote at a meeting of the\nCouncil, and shall not be a Member for any other purpose.",
        "footnotes": "",
        "query": "abv=CEN&statehandle=123456789/1362&actid=AC_CEN_9_67_00001_199373_1517807322617&sectionId=25579&sectionno=9&orderno=9&orgactid=AC_CEN_9_67_00001_199373_1517807322617"
      },
      {
        "sectionId": "25580",
        "sectionNo": "10",
        "orderNo": 10,
        "title": "Appointment of officers and other employees of the Council.",
        "content": "(1) For the purpose of enabling\nthe Council to discharge its functions efficiently under this Act, the Council shall, subject to such\nregulations as may be made in this behalf, appoint (whether on deputation or otherwise) such number of\nofficers and other employees as it may consider necessary:\n\nProvided that the category of posts equivalent to Group 'A' posts in the Central Government shall be\nsubject to the approval of the Central Government.\n\n(2) Every officer or other employee appointed by the Council shall be subject to such conditions of\nservice as may be determined by regulations.",
        "footnotes": "",
        "query": "abv=CEN&statehandle=123456789/1362&actid=AC_CEN_9_67_00001_199373_1517807322617&sectionId=25580&sectionno=10&orderno=10&orgactid=AC_CEN_9_67_00001_199373_1517807322617"
      },
      {
        "sectionId": "25581",
        "sectionNo": "11",
        "orderNo": 11,
        "title": "Authentication of the orders and other instruments of the Council.",
        "content": "All orders and decisions\nof the Council shall be authenticated by the signature of the Chairperson or any other Member authorised\nby the Council in this behalf, and all other instruments issued by the Council shall be authenticated by the\nsignature of the Member-Secretary or any other officer of the Council authorised in like manner in this\nbehalf by the Chairperson.",
        "footnotes": "",
        "query": "abv=CEN&statehandle=123456789/1362&actid=AC_CEN_9_67_00001_199373_1517807322617&sectionId=25581&sectionno=11&orderno=11&orgactid=AC_CEN_9_67_00001_199373_1517807322617"
      },
      {
        "sectionId": "25582",
        "sectionNo": "12",
        "orderNo": 12,
        "title": "Functions of the Council.",
        "content": "It shall be the duty of the Council to take all such steps as it may\nthink fit for ensuring planned and co-ordinated development of teacher education and for the\ndetermination and maintenance of standards for teacher education and for the purposes of performing its\nfunctions under this Act, the Council may--\n\n(a) undertake surveys and studies relating to various aspects of teacher education and publish the\nresult thereof;\n\n(b) make recommendations to the Central and State Government, Universities, University Grants\nCommission and recognised institutions in the matter of preparation of suitable plans and\nprogrammes in the field of teacher education;\n\n(c) co-ordinate and monitor teacher education and its development in the country;\n\n(d) lay down guidelines in respect of minimum qualifications for a person to be employed as a\nteacher ^1*** in recognised institutions;\n\n(e) lay down norms for any specified category of courses or trainings in teacher education,\nincluding the minimum eligibility criteria for admission thereof, and the method of selection of\ncandidates, duration of the course, course contents and mode of curriculum;\n\n(f) lay down guidelines for compliance by recognised institutions, for starting new courses or\ntraining, and for providing physical and instructional facilities, staffing pattern and staff qualification;\n\n(g) lay down standards in respect of examinations leading to teacher education qualifications,\ncriteria for admission to such examinations and schemes of courses or training;\n\n(h) lay down guidelines regarding tuition fees and other fees chargeable by recognised\ninstitutions;\n\n(i) promote and conduct innovation and research in various areas of teacher education and\ndisseminate the results thereof;\n\n(j) examine and review periodically the implementation of the norms, guidelines and standards\nlaid down by the Council, and to suitably advise the recognised institutions;\n\n(k) evolve suitable performance appraisal system, norms and mechanisms for enforcing\naccountability on recognised institutions;\n\n(l) formulate schemes for various levels of teacher education and identify recognised institutions\nand set up new institutions for teacher development programmes;\n\n(m) take all necessary steps to prevent commercialisation of teacher education; and\n\n(n) perform such other functions as may be entrusted to it by the Central Government.",
        "footnotes": "1. The words \"in schools or\" omitted by Act 18 of 2011, s. 5 (w.e.f. 1-6-2012).",
        "query": "abv=CEN&statehandle=123456789/1362&actid=AC_CEN_9_67_00001_199373_1517807322617&sectionId=25582&sectionno=12&orderno=12&orgactid=AC_CEN_9_67_00001_199373_1517807322617"
      },
      {
        "sectionId": "25583",
        "sectionNo": "12A",
        "orderNo": 13,
        "title": "Power of Council to determine minimum standards of education of school teachers.",
        "content": "^1[12A. Power of Council to determine minimum standards of education of school teachers. -- For\nthe purpose of maintaining standards of education in schools, the Council may, by regulations, determine\nthe qualifications of persons for being recruited as teachers in any pre-primary, primary, upper primary,\nsecondary, senior secondary or intermediate school or college, by whatever name called, established, run,\naided or recognised by the Central Government or a State Government or a local or other authority:\n\nProvided that nothing in this section shall adversely affect the continuance of any person recruited in\nany pre-primary, primary, upper primary, secondary, senior secondary or intermediate schools or\ncolleges, under any rule, regulation or order made by the Central Government, a State Government, a\nlocal or other authority, immediately before the commencement of the National Council for Teacher\nEducation (Amendment) Act, 2011 (18 of 2011) solely on the ground of non-fulfilment of such\nqualifications as may be specified by the Council:\n\nProvided further that the minimum qualifications of a teacher referred to in the first proviso shall be\nacquired within the period specified in this Act or under the Right of Children to Free and Compulsory\nEducation Act, 2009 (35 of 2009).]",
        "footnotes": "1 Ins. by Act 18 of 2011, s. 6 (w.e.f. 1-6-2012).",
        "query": "abv=CEN&statehandle=123456789/1362&actid=AC_CEN_9_67_00001_199373_1517807322617&sectionId=25583&sectionno=12A&orderno=13&orgactid=AC_CEN_9_67_00001_199373_1517807322617"
      },
      {
        "sectionId": "25584",
        "sectionNo": "13",
        "orderNo": 14,
        "title": "Inspection.",
        "content": "(1) For the purpose of ascertaining whether the recognised institutions are\nfunctioning in accordance with the provisions of this Act, the Council may cause inspection of any such\ninstitution, to be made by such persons as it may direct, and in such manner as may be prescribed.\n\n(2) The Council shall communicate to the institution the date on which inspection under\nsub-section (1) is to be made and the institution shall be entitled to be associated with the inspection in\nsuch manner as may be prescribed.\n\n(3) The Council shall communicate to the said institution, its views in regard to the results of any such\ninspection and may, after ascertaining the opinion of that institution, recommend to that institution the\naction to be taken as a result of such inspection.\n\n(4) All communications to the institution under this section shall be made to the executive authority\nthereof, and the executive authority of the institution shall report to the Council the action, if any, which\nis proposed to be taken for the purpose of implementing any such recommendation as is referred to in\nsub-section (3).",
        "footnotes": "",
        "query": "abv=CEN&statehandle=123456789/1362&actid=AC_CEN_9_67_00001_199373_1517807322617&sectionId=25584&sectionno=13&orderno=14&orgactid=AC_CEN_9_67_00001_199373_1517807322617"
      },
      {
        "sectionId": "25585",
        "sectionNo": "14",
        "orderNo": 15,
        "title": "Recognition of institutions offering course or training in teacher education.",
        "content": "(1) Every\ninstitution offering or intending to offer a course or training in teacher education on or after the appointed\nday, may, for grant of recognition under this Act, make an application to the Regional Committee\nconcerned in such form and in such manner as may be determined by regulations:\n\nProvided that an institution offering a course or training in teacher education immediately before the\nappointed day, shall be entitled to continue such course or training for a period of six months, if it has\nmade an application for recognition within the said period and until the disposal of the application by the\nRegional Committee.\n\n^1[Provided further that such institutions, as may be specified by the Central Government by\nnotification in the Official Gazette, which--\n\n(i) are funded by the Central Government or the State Government or the Union territory\nAdministration;\n\n(ii) have offered a course or training in teacher education on or after the appointed day till the\nacademic year 2017-2018; and\n\n(iii) fulfil the conditions specified under clause (a) of sub-section (3),\n\nshall be deemed to have been recognised by the Regional Committee.]\n\n(2) The fee to be paid along with the application under sub-section (1) shall be such as may be\nprescribed.\n\n(3) On receipt of an application by the Regional Committee from any institution under\nsub-section (1), and after obtaining from the institution concerned such other particulars as it may\nconsider necessary, it shall,--\n\n(a) if it is satisfied that such institution has adequate financial resources, accommodation, library,\nqualified staff, laboratory and that it fulfils such other conditions required for proper functioning of\nthe institution for a course or training in teacher education, as may be determined by regulations, pass\nan order granting recognition to such institution, subject to such conditions as may be determined by\nregulations; or\n\n(b) if it is of the opinion that such institution does not fulfil the requirements laid down in\nsub-clause (a), pass an order refusing recognition to such institution for reasons to be recorded in\nwriting:\n\nProvided that before passing an order under sub-clause (b), the Regional Committee shall provide a\nreasonable opportunity to the concerned institution for making a written representation.\n\n(4) Every order granting or refusing recognition to an institution for a course or training in teacher\neducation under sub-section (3) shall be published in the Official Gazette and communicated in writing\nfor appropriate action to such institution and to the concerned examining body, the local authority or the\nState Government and the Central Government.\n\n(5) Every institution, in respect of which recognition has been refused shall discontinue the course or\ntraining in teacher education from the end of the academic session next following the date of receipt of\nthe order refusing recognition passed under clause (b) of sub-section (3).\n\n(6) Every examining body shall, on receipt of the order under sub-section (4),--\n\n(a) grant affiliation to the institution, where recognition has been granted; or\n\n(b) cancel the affiliation of the institution, where recognition has been refused.",
        "footnotes": "1. The proviso ins. by Act 2 of 2019, s. 2 (w.e.f. 17.08.1995).",
        "query": "abv=CEN&statehandle=123456789/1362&actid=AC_CEN_9_67_00001_199373_1517807322617&sectionId=25585&sectionno=14&orderno=15&orgactid=AC_CEN_9_67_00001_199373_1517807322617"
      },
      {
        "sectionId": "25586",
        "sectionNo": "15",
        "orderNo": 16,
        "title": "Permission for a new course or training by recognised institution.",
        "content": "(1) Where any recognised\ninstitution intends to start any new course or training in teacher education, it may make an application to\nseek permission therefor to the Regional Committee concerned in such form and in such manner as may\nbe determined by regulations.\n\n^1[Provided that the course or training in teacher education offered on or after the appointed day till the\nacademic year 2017-2018 by such institutions, as may be specified by the Central Government by\nnotification in the Official Gazette, which--\n\n(i) are funded by the Central Government or the State Government or the Union territory\nAdministration; and\n\n(ii) fulfil the conditions specified under clause (a) of sub-section (3),\n\nshall be deemed to have been granted permission by the Regional Committee.]\n\n(2) The fees to be paid along with the application under sub-section (1) shall be such as may be\nprescribed.\n\n(3) On receipt of an application from an institution under sub-section (1), and after obtaining from the\nrecognised institution such other particulars as may be considered necessary, the Regional Committee\nshall,--\n\n(a) if it is satisfied that such recognised institution has adequate financial resources,\naccommodation, library, qualified staff, laboratory, and that it fulfils such other conditions required\nfor proper conduct of the new course or training in teacher education, as may be determined by\nregulations, pass an order granting permission, subject to such conditions as may be determined by\nregulations; or\n\n(b) if it is of the opinion that such institution does not fulfil the requirements laid down in\nsub-clause (a), pass an order refusing permission to such institution for reasons to be recorded in\nwriting:\n\nProvided that before passing an order refusing permission under sub-class (b), the Regional\nCommittee shall provide a reasonable opportunity to the institution concerned for making a written\nrepresentation.\n\n(4) Every order granting or refusing permission to a recognised institution for a new course or\ntraining in teacher education under sub-section (3), shall be published in the Official Gazette and\ncommunicated in writing for appropriate action to such recognised institution and to the concerned\nexamining body, the local authority, the State Government and the Central Government.",
        "footnotes": "1. The proviso ins. by s. 3, ibid. (w.e.f. 17.08.1995).",
        "query": "abv=CEN&statehandle=123456789/1362&actid=AC_CEN_9_67_00001_199373_1517807322617&sectionId=25586&sectionno=15&orderno=16&orgactid=AC_CEN_9_67_00001_199373_1517807322617"
      },
      {
        "sectionId": "25587",
        "sectionNo": "16",
        "orderNo": 17,
        "title": "Affiliating body to grant affiliation after recognition or permission by the Council.",
        "content": "Notwithstanding anything contained in any other law for the time being in force, no examining body\nshall, on or after the appointed day,--\n\n(a) grant affiliation, whether provisional or otherwise, to any institution; or\n\n(b) hold examination, whether provisional or otherwise, for a course or training conducted by a\nrecognised institution,\nunless the institution concerned has obtained recognition from the Regional Committee concerned, under\nsection 14 or permission for a course or training under section 15.",
        "footnotes": "",
        "query": "abv=CEN&statehandle=123456789/1362&actid=AC_CEN_9_67_00001_199373_1517807322617&sectionId=25587&sectionno=16&orderno=17&orgactid=AC_CEN_9_67_00001_199373_1517807322617"
      },
      {
        "sectionId": "25588",
        "sectionNo": "17",
        "orderNo": 18,
        "title": "Contravention of provisions of the Act and consequences thereof.",
        "content": "(1) Where the Regional\nCommittee is, on its own motion or on any representation received from any person, satisfied that a\nrecognised institution has contravened any of the provisions of this Act, or the rules, regulations, orders\nmade or issued thereunder, or any condition subject to which recognition under sub-section (3) of\nsection 14 or permission under sub-section (3) of section 15 was granted, it may withdraw recognition of\nsuch recognised institution, for reasons to be recorded in writing:\n\nProvided that no such order against the recognised institution shall be passed unless a reasonable\nopportunity of making representation against the proposed order has been given to such recognised\ninstitution:\n\nProvided further that the order withdrawing or refusing recognition passed by the Regional\nCommittee shall come into force only with effect from the end of the academic session next following the\ndate of communication of such order.\n\n(2) A copy of every order passed by the Regional Committee under sub-section (1),--\n\n(a) shall be communicated to the recognised institution concerned and a copy thereof shall also be\nforwarded simultaneously to the University or the examining body to which such institution was\naffiliated for cancelling affiliation; and--\n\n(b) shall be published in the Official Gazette for general information.\n\n(3) Once the recognition of a recognised institution is withdrawn under sub-section (1), such\ninstitution shall discontinue the course or training in teacher education, and the concerned University or\nthe examining body shall cancel affiliation of the institution in accordance with the order passed under\nsub-section (1), with effect from the end of the academic session next following the date of\ncommunication of the said order.\n\n(4) If an institution offers any course or training in teacher education after the coming into force of\nthe order withdrawing recognition under sub-section (1), or where an institution offering a course or\ntraining in teacher education immediately before the appointed day fails or neglects to obtain recognition\nor permission under this Act, the qualification in teacher education obtained pursuant to such course or\ntraining or after undertaking a course or training in such institution, shall not be treated as a valid\nqualification for purposes of employment under the Central Government, any State Government or\nUniversity, or in any school, college or other educational body aided by the Central Government or any\nState Government.",
        "footnotes": "",
        "query": "abv=CEN&statehandle=123456789/1362&actid=AC_CEN_9_67_00001_199373_1517807322617&sectionId=25588&sectionno=17&orderno=18&orgactid=AC_CEN_9_67_00001_199373_1517807322617"
      },
      {
        "sectionId": "25589",
        "sectionNo": "18",
        "orderNo": 19,
        "title": "Appeals.",
        "content": "(1) Any person aggrieved by an order made under section 14 or section 15 or\nsection 17 of the Act may prefer an appeal to the Council within such period as may be prescribed.\n\n(2) No appeal shall be admitted if it is preferred after the expiry of the period prescribed therefor:\n\nProvided that an appeal may be admitted after the expiry of the period prescribed therefor, if the\nappellant satisfies the Council that he had sufficient cause for not preferring the appeal within the\nprescribed period.\n\n(3) Every appeal made under this section shall be made in such form and shall be accompanied by a\ncopy of the order appealed against and by such fees as may be prescribed.\n\n(4) The procedure for disposing of an appeal shall be such as may be prescribed:\n\nProvided that before disallowing an appeal, the appellant shall be given a reasonable opportunity to\nrepresent its case.\n\n(5) The Council may confirm or reverse the order appealed against.",
        "footnotes": "",
        "query": "abv=CEN&statehandle=123456789/1362&actid=AC_CEN_9_67_00001_199373_1517807322617&sectionId=25589&sectionno=18&orderno=19&orgactid=AC_CEN_9_67_00001_199373_1517807322617"
      },
      {
        "sectionId": "25590",
        "sectionNo": "19",
        "orderNo": 20,
        "title": "Executive Committee.",
        "content": "(1) The Council shall constitute a Committee, called Executive\nCommittee for discharging such functions as may be assigned to it by the Council or as may be\ndetermined by regulations.\n\n(2) The Executive Committee shall consist of the following members, namely:--\n\n(a) the Chairperson;\n\n(b) the Vice-Chairperson;\n\n(c) the Member-Secretary;\n\n(d) the Secretary to the Government of India in the Department dealing with\nEducation, ex officio;\n\n(e) the Secretary, University Grants Commission, ex officio;\n\n(f) the Director, National Council of Educational Research and Training, ex officio;\n\n(g) the Financial Adviser to the Government of India in the Department dealing with\nEducation, ex officio;\n\n(h) four experts in teacher education to be nominated by the Central Government;\n\n(i) four State representatives to be nominated by the Central Government in such manner as may\nbe prescribed;\n\n(j) the Chairpersons of the Regional Committees.\n\n(3) The Chairperson and the Member-Secretary of the Council shall respectively, function as the\nChairperson and the Member-Secretary of the Executive Committee.\n\n(4) The Chairperson or in his absence, the Vice-Chairperson of the Council shall preside at the\nmeetings of the Executive Committee and in the absence of both the Chairperson and the\nVice-Chairperson, any other member chosen by the members present at the meeting shall preside at the\nmeeting.\n\n(5) The quorum necessary for the transaction of business at the meetings of the Executive Committee\nshall be as laid down by regulations.\n\n(6) The Executive Committee may co-opt, in such manner and for such purposes, as may be\ndetermined by regulations, not more than two persons whose assistance and advice, it may desire in\ncarrying out any of the functions assigned to the Executive Committee:\n\nProvided that the persons co-opted by the Executive Committee for any purpose shall have a right to\ntake part in the discussions relevant to that purpose, but shall not have a right to vote at a meeting of the\nExecutive Committee, and shall not be a member for any other purpose.\n\n(7) The Council may, if it considers necessary, establish such other committees, for such specific\npurpose, as it may deem fit.",
        "footnotes": "",
        "query": "abv=CEN&statehandle=123456789/1362&actid=AC_CEN_9_67_00001_199373_1517807322617&sectionId=25590&sectionno=19&orderno=20&orgactid=AC_CEN_9_67_00001_199373_1517807322617"
      },
      {
        "sectionId": "25591",
        "sectionNo": "20",
        "orderNo": 21,
        "title": "Regional Committees.",
        "content": "(1) The Council shall, by notification in the Official Gazette, establish\nthe following Regional Committees, namely:--\n\n(i) the Eastern Regional Committee;\n\n(ii) the Western Regional Committee;\n\n(iii) the Northern Regional Committee; and\n\n(iv) the Southern Regional Committee.\n\n(2) The Council may, if it considers necessary, establish with the approval of the Central\nGovernment, such other Regional Committees as it may deem fit.\n\n(3) The Regional Committee shall consist of the following members, namely:--\n\n(a) a Member to be nominated by the Council;\n\n(b) one representative from each of the States and the Union territories of the region, to be\nnominated by the respective States and the Union territories;\n\n(c) such number of persons, having special knowledge and experience in matters relating to\nteacher education, as may be determined by regulations.\n\n(4) The Council shall nominate one of the members of the concerned Regional Committee to function\nas the chairperson of the said Committee.\n\n(5) The term of office of the members referred to in clause (c) and the allowances payable to such\nmembers shall be such as may be determined by regulations.\n\n(6) The Regional Committee shall, in addition to its functions under sections 14, 15 and 17, perform\nsuch other functions, as may be assigned to it by the Council or as may be determined by regulations.\n\n(7) The functions of, the procedure to the followed by, the territorial jurisdiction of, and the manner\nof filling casual vacancies among members of, a Regional Committee shall be such as may be determined\nby regulations.",
        "footnotes": "",
        "query": "abv=CEN&statehandle=123456789/1362&actid=AC_CEN_9_67_00001_199373_1517807322617&sectionId=25591&sectionno=20&orderno=21&orgactid=AC_CEN_9_67_00001_199373_1517807322617"
      },
      {
        "sectionId": "25592",
        "sectionNo": "21",
        "orderNo": 22,
        "title": "Power to terminate the Regional Committee.",
        "content": "(1) If the Council is of the opinion that a\nRegional Committee is unable to perform, or has persistently made default in the performance of the\nduties imposed on it by or under this Act or has exceeded or abused its powers, or has wilfully or without\nsufficient cause, failed to comply with any direction issued by the Council for carrying out the provisions\nof this Act, the Council may, by notification in the Official Gazette, terminate forthwith the Regional\nCommittee.\n\n(2) Upon the publication of a notification under sub-section (1),--\n\n(a) all members of the Regional Committee shall, notwithstanding that their term of office had\nnot expired, as from the date of the termination, vacate their office as such members; and\n\n(b) all the powers and duties which may, by or under the provisions of this Act be exercised or\nperformed by or on behalf of the Regional Committee shall, during the period when the term of office\nof its members stand terminated, be exercised and performed by such person or persons as the\nCouncil may direct.\n\n(3) The Council may at any time after publication of a notification under sub-section (2), re-constitute\nthe Regional Committee in the manner provided in sub-section (3) of section 20:\n\nProvided that it shall be competent for the Council to appoint any person, who was a member of a\nRegional Committee which was terminated, as a member of the reconstituted Regional Committee.",
        "footnotes": "",
        "query": "abv=CEN&statehandle=123456789/1362&actid=AC_CEN_9_67_00001_199373_1517807322617&sectionId=25592&sectionno=21&orderno=22&orgactid=AC_CEN_9_67_00001_199373_1517807322617"
      },
      {
        "sectionId": "25593",
        "sectionNo": "22",
        "orderNo": 23,
        "title": "Payment to the Council.",
        "content": "The Central Government may, after due appropriation made by\nParliament by law in this behalf, pay to the Council in each financial year such sums as may be\nconsidered necessary for the performance of the functions of the Council under this Act.",
        "footnotes": "",
        "query": "abv=CEN&statehandle=123456789/1362&actid=AC_CEN_9_67_00001_199373_1517807322617&sectionId=25593&sectionno=22&orderno=23&orgactid=AC_CEN_9_67_00001_199373_1517807322617"
      },
      {
        "sectionId": "25594",
        "sectionNo": "23",
        "orderNo": 24,
        "title": "Fund of the Council.",
        "content": "(1) The Council shall have its own fund; and all sums which may, from\ntime to time, be paid to it by the Central Government or a State Government and all the receipts of the\nCouncil, including any sum which any other authority or person in India or abroad may pay to the\nCouncil, shall be credited to the fund and all payments by the Council shall be made therefrom.\n\n(2) All moneys belonging to the fund shall be deposited in such banks or invested in such manner as\nmay be decided by the Council.\n\n(3) The Council may spend such sums as it thinks fit for performing its functions under this Act, and\nsuch sums shall be treated as expenditure payable out of the fund of the Council.",
        "footnotes": "",
        "query": "abv=CEN&statehandle=123456789/1362&actid=AC_CEN_9_67_00001_199373_1517807322617&sectionId=25594&sectionno=23&orderno=24&orgactid=AC_CEN_9_67_00001_199373_1517807322617"
      },
      {
        "sectionId": "25595",
        "sectionNo": "24",
        "orderNo": 25,
        "title": "Budget of the Council.",
        "content": "The Council shall prepare, in such form and at such time each year as\nmay be prescribed, a budget in respect of the financial year next ensuing, showing the estimated receipts\nand expenditure, and copies thereof shall be forwarded to the Central Government.",
        "footnotes": "",
        "query": "abv=CEN&statehandle=123456789/1362&actid=AC_CEN_9_67_00001_199373_1517807322617&sectionId=25595&sectionno=24&orderno=25&orgactid=AC_CEN_9_67_00001_199373_1517807322617"
      },
      {
        "sectionId": "25596",
        "sectionNo": "25",
        "orderNo": 26,
        "title": "Annual report.",
        "content": "The Council shall prepare once every year, in such form and at such time as\nmay be prescribed, an annual report giving a true and full account of its activities during the previous year\nand copies thereof shall be forwarded to the Central Government and that Government shall cause the\nsame to be laid before both Houses of Parliament.",
        "footnotes": "",
        "query": "abv=CEN&statehandle=123456789/1362&actid=AC_CEN_9_67_00001_199373_1517807322617&sectionId=25596&sectionno=25&orderno=26&orgactid=AC_CEN_9_67_00001_199373_1517807322617"
      },
      {
        "sectionId": "25597",
        "sectionNo": "26",
        "orderNo": 27,
        "title": "Accounts and audit.",
        "content": "(1) The Council shall cause to be maintained such books of account in\nsuch form and in such manner and as the Central Government may, in consultation with the Comptroller\nand Auditor-General of India, prescribe.\n\n(2) The Council shall, as soon as may be, after closing its annual accounts, prepare a statement of\naccounts in such form and forward the same to the Comptroller and Auditor-General of India by such date\nas the Central Government may, in consultation with the Comptroller and Auditor-General, determine.\n\n(3) The accounts of the Council shall be audited by the Comptroller and Auditor-General of India at\nsuch times and in such manner as he think fit.\n\n(4) The accounts of the Council as certified by the Comptroller and Auditor-General of India or any\nother person appointed by him in this behalf, together with the audit report thereon shall be forwarded\nannually to the Central Government and that Government shall cause the same to be laid before both\nHouses of Parliament.",
        "footnotes": "",
        "query": "abv=CEN&statehandle=123456789/1362&actid=AC_CEN_9_67_00001_199373_1517807322617&sectionId=25597&sectionno=26&orderno=27&orgactid=AC_CEN_9_67_00001_199373_1517807322617"
      },
      {
        "sectionId": "25598",
        "sectionNo": "27",
        "orderNo": 28,
        "title": "Delegation of powers and functions.",
        "content": "The Council may, by general or special order in writing,\ndelegate to the chairperson or to any other member or to any officer of the Regional Committee, subject\nto such conditions and limitations, if any, as may be specified in the order, such of its powers and\nfunctions under this Act (except the power to make regulations under section 32), as it may deem\nnecessary.",
        "footnotes": "",
        "query": "abv=CEN&statehandle=123456789/1362&actid=AC_CEN_9_67_00001_199373_1517807322617&sectionId=25598&sectionno=27&orderno=28&orgactid=AC_CEN_9_67_00001_199373_1517807322617"
      },
      {
        "sectionId": "25599",
        "sectionNo": "28",
        "orderNo": 29,
        "title": "Protection of action taken in good faith.",
        "content": "No prosecution or other legal proceeding shall lie\nagainst the Central Government, the Council or any committees appointed by it, or any Member of the\nCouncil or member of such committees, or any officer or employee of the Central Government or the\nCouncil or any other person authorised by that Government or the Council, for anything which is in good\nfaith done or intended to be done under this Act or the rules or regulations made thereunder.",
        "footnotes": "",
        "query": "abv=CEN&statehandle=123456789/1362&actid=AC_CEN_9_67_00001_199373_1517807322617&sectionId=25599&sectionno=28&orderno=29&orgactid=AC_CEN_9_67_00001_199373_1517807322617"
      },
      {
        "sectionId": "25600",
        "sectionNo": "29",
        "orderNo": 30,
        "title": "Directions by the Central Government.",
        "content": "(1) The Council shall, in the discharge of its functions\nand duties under this Act be bound by such directions on questions of policy as the Central Government\nmay give in writing to it from time to time.\n\n(2) The decision of the Central Government as to whether a question is one of policy or not shall be\nfinal.",
        "footnotes": "",
        "query": "abv=CEN&statehandle=123456789/1362&actid=AC_CEN_9_67_00001_199373_1517807322617&sectionId=25600&sectionno=29&orderno=30&orgactid=AC_CEN_9_67_00001_199373_1517807322617"
      },
      {
        "sectionId": "25601",
        "sectionNo": "30",
        "orderNo": 31,
        "title": "Power to supersede the Council.",
        "content": "(1) If the Central Government is of the opinion that the\nCouncil is unable to perform, or has persistently made default in the performance of the duties imposed\non it by or under this Act or has exceeded or abused its power, or has wilfully or without sufficient cause\nfailed to comply with any direction issued by the Central Government under section 29, the Central\nGovernment may, by notification in the Official Gazette, supersede the Council for such period as may be\nspecified in the notification:\n\nProvided that before issuing a notification under this sub-section, the Central Government shall give\nreasonable opportunity to the Council to show cause why it should not be superseded and shall consider\nthe explanation and objections, if any, of the Council.\n\n(2) Upon the publication of a notification under sub-section (1) superseding the Council--\n\n(a) all the Members of the Council shall, notwithstanding that their term of office had not expired,\nas from the date of supersession, vacate their offices as such Members;\n\n(b) all the powers and duties which may, by or under the provisions of this Act be exercised or\nperformed by or on behalf of the Council shall, during the period of supersession, be exercised and\nperformed by such person or persons as the Central Government may direct;\n\n(c) all property vested in the Council shall, during the period of supersession, vest in the Central\nGovernment.\n\n(3) On the expiry of the period of supersession specified in the notification issued under\nsub-section (1), the Central Government, may--\n\n(a) extend the period of supersession for such further period as it may consider necessary; or\n\n(b) reconstitute the Council in the manner provided in section 3.",
        "footnotes": "",
        "query": "abv=CEN&statehandle=123456789/1362&actid=AC_CEN_9_67_00001_199373_1517807322617&sectionId=25601&sectionno=30&orderno=31&orgactid=AC_CEN_9_67_00001_199373_1517807322617"
      },
      {
        "sectionId": "25602",
        "sectionNo": "31",
        "orderNo": 32,
        "title": "Power to make rules.",
        "content": "(1) The Central Government may, by notification in the Official Gazette,\nmake rules to carry out the provisions of this Act.\n\n(2) In particular, and without prejudice to the generality of the foregoing powers, such rules may\nprovide for all or any of the following matters, namely:--\n\n(a) the manner in which Central Government is to appoint experts to the Council under\nsub-clause (v) of clause (m) of sub-section (4) of section 3;\n\n(b) the manner in which the Central Government is to appoint Members to the Council from\namongst the States and the Union territory Administrations under clause (n) of sub-section (4) of\nsection 3;\n\n(c) the conditions of service of the Chairperson, the Vice-Chairperson and the Member-Secretary\nunder sub-section (3) and of Members under sub-section (4) of section 4;\n\n(d) the powers and duties of the Chairperson under sub-section (7) of section 4;\n\n(e) the manner in which and the persons by whom the inspection of an institution is to be made\nand the manner in which the institution is to be associated in such inspection under sub-sections (1)\nand (2) of section 13;\n\n(f) the fees payable on application for obtaining recognition under sub-section (2) of section 14\nand for obtaining permission under sub-section (2) of section 15;\n\n(g) the period of limitation for an appeal under sub-section (1) of section 18, the form in which\nsuch appeal is to be made and the fees payable therefor under sub-section (3) of that section and the\nprocedure for disposal of an appeal under sub-section (4) of that section;\n\n(h) the manner in which the Central Government is to nominate the State representatives in the\nExecutive Committee under clause (i) of sub-section (2) of section 19;\n\n(i) the form in which and the time within which the budget under section 24 and the annual report\nunder section 25 of the Council is to be prepared;\n\n(j) the manner and the form in which the accounts of the Council are to be maintained under\nsub-section (1) of section 26;\n\n(k) any other matter which has to be, or may be, prescribed.",
        "footnotes": "",
        "query": "abv=CEN&statehandle=123456789/1362&actid=AC_CEN_9_67_00001_199373_1517807322617&sectionId=25602&sectionno=31&orderno=32&orgactid=AC_CEN_9_67_00001_199373_1517807322617"
      },
      {
        "sectionId": "25603",
        "sectionNo": "32",
        "orderNo": 33,
        "title": "Power to make regulations.",
        "content": "(1) The Council may, by notification in the Official Gazette, make\nregulations not inconsistent with the provisions of this Act and the rules made thereunder, generally to\ncarry out the provisions of this Act.\n\n(2) In particular, and without prejudice to the generality of the foregoing power, such regulations may\nprovide for all or any of the following matters, namely:--\n\n(a) the time and the place of the meetings of the Council and the procedure for conducting\nbusiness thereat under sub-section (1) of section 7;\n\n(b) the manner in which and the purposes for which persons may be co-opted by the Council\nunder sub-section (1) of section 9;\n\n(c) the appointment and terms and conditions of service of officers and other employees of the\nCouncil under sub-sections (1) and (2) respectively of section 10;\n\n(d) the norms, guidelines and standards in respect of--\n\n(i) the minimum qualifications for a person to be employed as a teacher under clause (d) of\nsection 12;\n\n(ii) the specified category of courses or training in teacher education under clause (e) of\nsection 12;\n\n(iii) starting of new courses or training in recognised institutions under clause (f) of\nsection 12;\n\n(iv) standards in respect of examinations leading to teacher education qualifications referred\nto in clause (g) of section 12;\n\n(v) the tuition fees and other fees chargeable by institutions under clause (h) of section 12;\n\n(vi) the schemes for various levels of teacher education, and identification of institutions for\noffering teacher development programmes under clause (l) of section 12;\n\n^1[(dd) the qualifications of teachers under section 12A;]\n\n(e) the form and the manner in which an application for recognition is to be submitted under\nsub-section (1) of section 14;\n\n(f) conditions required for the proper functioning of the institution and conditions for granting\nrecognition under clause (a) of sub-section (3) of section 14;\n\n(g) the form and the manner in which an application for permission is to be made under\nsub-section (1) of section 15;\n\n(h) conditions required for the proper conduct of a new course or training and conditions for\ngranting permission under clause (a) of sub-section (3) of section 15;\n\n(i) the functions which may be assigned by the Council to the Executive Committee under\nsub-section (1) of section 19;\n\n(j) the procedure and the quorum necessary for transaction of business at the meetings of the\nExecutive Committee under sub-section (5) of section 19;\n\n(k) the manner in which and the purposes for which the Executive Committee may co-opt persons\nunder sub-section (6) of section 19;\n\n(l) the number of persons under clause (c) of sub-section (3) of section 20;\n\n(m) the term of office and allowances payable to members under sub-section (5) of section 20;\n\n(n) additional functions to be performed by the Regional Committee under sub-section (6) of\nsection 20;\n\n(o) the functions of, the procedure to be followed by, the territorial jurisdiction of, and the manner\nof filling casual vacancies among members of, a Regional Committee under sub-section (7) of\nsection 20;\n\n(p) any other matter in respect of which provision is to be, or may be, made by regulations.",
        "footnotes": "1 Ins. by Act 18 of 2011, s. 7 (w.e.f. 1-6-2012).",
        "query": "abv=CEN&statehandle=123456789/1362&actid=AC_CEN_9_67_00001_199373_1517807322617&sectionId=25603&sectionno=32&orderno=33&orgactid=AC_CEN_9_67_00001_199373_1517807322617"
      },
      {
        "sectionId": "25604",
        "sectionNo": "33",
        "orderNo": 34,
        "title": "Rules and regulations to be laid before Parliament.",
        "content": "Every rule and every regulation made\nunder this Act shall be laid, as soon as may be after it is made, before each House of Parliament, while it\nis in session, for a total period of thirty days which may be comprised in one session or in two or more\nsuccessive sessions, and if, before the expiry of the session immediately following the session or the\nsuccessive sessions aforesaid, both House agree in making any modification in the rule or regulation, or\nboth House agree that the rule or regulation should not be made, the rule or regulation shall thereafter\nhave effect only in such modified form or be of no effect, as the case may be; so, however, that any such\nmodification or annulment shall be without prejudice to the validity of anything previously done under\nthat rule or regulation.",
        "footnotes": "",
        "query": "abv=CEN&statehandle=123456789/1362&actid=AC_CEN_9_67_00001_199373_1517807322617&sectionId=25604&sectionno=33&orderno=34&orgactid=AC_CEN_9_67_00001_199373_1517807322617"
      },
      {
        "sectionId": "25605",
        "sectionNo": "34",
        "orderNo": 35,
        "title": "Power to remove difficulties.",
        "content": "(1) If any difficulty arises in giving effect to the provisions of\nthis Act, the Central Government may, by order, published in the Official Gazette, make such provisions\nnot inconsistent with the provisions of this Act as may appear to be necessary for removing the difficulty:\n\nProvided that no order shall be made under this section after the expiry of two years from the\ncommencement of this Act.\n\n(2) Every order made under this section shall be laid, as soon as may be after it is made, before each\nHouse of Parliament.",
        "footnotes": "",
        "query": "abv=CEN&statehandle=123456789/1362&actid=AC_CEN_9_67_00001_199373_1517807322617&sectionId=25605&sectionno=34&orderno=35&orgactid=AC_CEN_9_67_00001_199373_1517807322617"
      }
    ],
    "hindiTitle": "राष्ट्री य अध्यापक शिक्षा परिषद्अधिनियम, 1993",
    "actYear": "1993",
    "ministry": "Ministry of Education",
    "department": "Department of School Education and Literacy",
    "longTitle": "An Act to provide for the establishment of a National Council for Teacher Education with a view to achieving planned and co-ordinated development of the teacher education system throughout the country, the regulation and proper maintenance of norms and standards in the teacher education system including qualifications of school teachers and for matters connected therewith.",
    "enforcementDate": "01-07-1995",
    "notification": "1st July, 1995, vide notification No. S.O. 620(E), dated 1st July, 1995, see Gazette of India, Extraordinary, Part II, sec. 3(ii)."
  }
}
