{
  "cacheVersion": 1,
  "fetchedAt": "2026-05-09T00:38:00.370Z",
  "sourceUrl": "https://www.indiacode.nic.in/handle/123456789/19224",
  "completeFetch": true,
  "maxSections": null,
  "law": {
    "slug": "the-north-western-provinces-and-oudh-act-1890",
    "handle": "19224",
    "collectionHandle": "123456789/1362",
    "title": "The North-western Provinces and Oudh Act, 1890",
    "actNumber": "20",
    "enactmentDate": "1890-10-16",
    "sourceUrl": "https://www.indiacode.nic.in/handle/123456789/19224",
    "sources": {
      "en": [
        {
          "kind": "html",
          "url": "https://www.indiacode.nic.in/handle/123456789/19224"
        },
        {
          "kind": "pdf",
          "url": "https://www.indiacode.nic.in/bitstream/123456789/19224/1/a189020.pdf",
          "title": "The North-western Provinces and Oudh Act, 1890"
        },
        {
          "kind": "pdf",
          "url": "https://www.indiacode.nic.in/help/userGuide.pdf",
          "title": "User Guide"
        }
      ],
      "hi": [
        {
          "kind": "pdf",
          "url": "https://www.indiacode.nic.in/bitstream/123456789/19224/3/H1890-20.pdf",
          "title": "पश्‍चिमोत्तर प्रान्‍त और अवध अधिनियम, 1890"
        }
      ]
    },
    "sections": [
      {
        "sectionId": "70499",
        "sectionNo": "1",
        "orderNo": 1,
        "title": "Title.",
        "content": "This Act may be called the North-Western Provinces and Oudh Act, 1890.",
        "footnotes": "",
        "query": "abv=CEN&statehandle=123456789/1362&actid=AC_CEN_5_5_00114_189020_1666335792135&sectionId=70499&sectionno=1&orderno=1&orgactid=AC_CEN_5_5_00114_189020_1666335792135"
      },
      {
        "sectionId": "70500",
        "sectionNo": "2",
        "orderNo": 2,
        "title": "Commencement of Part I.",
        "content": "This Part shall come into force on such day^1\nas the said LieutenantGovernor may, by notification in the Official Gazette, direct.",
        "footnotes": "",
        "query": "abv=CEN&statehandle=123456789/1362&actid=AC_CEN_5_5_00114_189020_1666335792135&sectionId=70500&sectionno=2&orderno=2&orgactid=AC_CEN_5_5_00114_189020_1666335792135"
      },
      {
        "sectionId": "70501",
        "sectionNo": "3",
        "orderNo": 3,
        "title": "3 and 4 Repealed.",
        "content": "Amendment of Act 19 of 1873. Rep. by the United Provinces Land-revenue Act, 1901\n(U.P. Act 3 of 1901).\n\nAnd whereas it has been determined to annex the Jhansi Division, comprising the districts of Jhansi,\nJalaun and Lalatpur, to the Allahabad Division;\nAnd whereas the said Jhansi Division is a Schedule District under the Scheduled Districts\nAct, 1874; (14 of 1874);^2\n\nAnd whereas it is expedient that the law in force in the same division should, on such annexation, be\nthe same as the law in force in the temporarily-settled districts comprised in the Allahabad Division, and\nthat the said division should cease to be a Schedule District;\n\nIt is hereby enacted as follows:—",
        "footnotes": "1. The 1st April, 1891, see North-Western Provinces and Oudh Gazette,1891, Pt. I, p. 130.\n\n2. Since rep. by the A.O. 1937",
        "query": "abv=CEN&statehandle=123456789/1362&actid=AC_CEN_5_5_00114_189020_1666335792135&sectionId=70501&sectionno=3&orderno=3&orgactid=AC_CEN_5_5_00114_189020_1666335792135"
      },
      {
        "sectionId": "70502",
        "sectionNo": "5",
        "orderNo": 4,
        "title": "Laws in force in certain districts of the Allahabad Division to apply to Jhansi.",
        "content": "(1) All\nenactments which shall on the day^1 when this Part comes into force be in force in the said temporarilysettled districts and not in the said Jhansi Division shall be deemed to come into force in that Division\non and from the said day^1.\n(2) Except the Jhansi Encumbered Estates Act, 1882, (16 of 1882)^2\nand the Jhansi and Morar\nAct, 1886,(17 of 1886)^3\nall enactments which shall on the said day^1\nbe in force in the said division and\nnot in the said temporarily settled districts, including the Jhansi Courts Act, 1867 (18 of 1867), and\nAct No. 27 of 1867, shall be deemed to be repealed on and from the said day^1\nin the said division.",
        "footnotes": "1. That is, the 1st April, 1891.\n\n2. Since rep. by the Bundelkhand\nEncumbered Estates Act, 1903 (U.P. 1 of 1903).\n\n3. Rep. by Act 42 of 1953.",
        "query": "abv=CEN&statehandle=123456789/1362&actid=AC_CEN_5_5_00114_189020_1666335792135&sectionId=70502&sectionno=5&orderno=4&orgactid=AC_CEN_5_5_00114_189020_1666335792135"
      },
      {
        "sectionId": "70503",
        "sectionNo": "6",
        "orderNo": 5,
        "title": "[Repealed.].",
        "content": "Rep. by the Bundelkhand Encumbered Estates Act, 1903 (U.P.\nAct 1 of 1903).",
        "footnotes": "",
        "query": "abv=CEN&statehandle=123456789/1362&actid=AC_CEN_5_5_00114_189020_1666335792135&sectionId=70503&sectionno=6&orderno=5&orgactid=AC_CEN_5_5_00114_189020_1666335792135"
      },
      {
        "sectionId": "70564",
        "sectionNo": "7",
        "orderNo": 6,
        "title": "Discharge of functions assigned to Deputy Commissioner and Commissioner by Act 17 of 1866.",
        "content": "The functions assigned to the Deputy Commissioner and the Commissioner by the Jhansi and\nMorar Act, 1886^1\n(17 of 1886), shall be discharged by the District Judge and the High Court,\nrespectively, and references to Courts in the Jhansi district subordinate to the Commissioner shall be\ndeemed to apply to the Civil Courts established in that district under the Bengal, ^2North-Western\nProvinces and Assam Civil Courts Act, 1887 (12 of 1887).",
        "footnotes": "1. Rep. by Act 42 of 1953.\n\n2. “Agra” has been subs. for “North-Western Provinces” by Act 16 of 1911.",
        "query": "abv=CEN&statehandle=123456789/1362&actid=AC_CEN_5_5_00114_189020_1666335792135&sectionId=70564&sectionno=7&orderno=6&orgactid=AC_CEN_5_5_00114_189020_1666335792135"
      },
      {
        "sectionId": "70505",
        "sectionNo": "8",
        "orderNo": 7,
        "title": "Jhansi Division to cease to be a Scheduled District.",
        "content": "(1) On and from the said day^1\nthe said\ndivision shall cease to be a Schedule District ^2***.",
        "footnotes": "1. That is, the 1st April, 1891.\n\n2. The second clause of sub-section (1), and sub-section (2) were rep. by Act 1 of 1938, s. 2 and Sch",
        "query": "abv=CEN&statehandle=123456789/1362&actid=AC_CEN_5_5_00114_189020_1666335792135&sectionId=70505&sectionno=8&orderno=7&orgactid=AC_CEN_5_5_00114_189020_1666335792135"
      },
      {
        "sectionId": "70506",
        "sectionNo": "9",
        "orderNo": 8,
        "title": "Application of Act 12 of 1887 to Jhansi, and disposal of pending cases.",
        "content": "^1***\n(2) All cases or proceedings pending in any Civil Court in the said division on the said day^2\nshall\nbe disposed of as follows:—\n\n(a) if pending in theCourt of a Tahsildar or of an Assistant Commissioner of the second class—\nby the Munsif;\n\n(b) if pending in the Court of an Assistant Commissioner of the first class—by the Subordinate\nJudge;\n\n(c) if pending in the Court of a Deputy Commissioner—by the District Judge;\n\n(d) if pending in the Court of the Commissioner—by the District Judge, unless the case\npending is an appeal from a decree or order of the Deputy Commissioner, in which case the appeal\nshall be disposed of by the High Court.\n\n(3) For the purposes of sections 20 to 22, both inclusive, of the Bengal, ^3North-Western Provinces\nand Assam Civil Courts Act, 1887 (12 of 1887), all decrees and orders passed by Civil Courts in the\nsaid division and not appealed against before the said day3\nshall be deemed—\n\n(a) if passed by the Court of a Tahsildar or an Assistant Commissioner of the second class—to\nhave been passed by a Munsif;\n\n(b) if passed by the Court of an Assistant Commissioner of the first class—to have been passed\nby a Subordinate Judge;\n\n(c) if passed by the Court of a Deputy Commissioner or the Commissioner—to have been\npassed by a District Judge.\n\n(4) Where any Civil Court ceases by reason of the passing of this Act to have jurisdiction with\nrespect to any case, any proceeding in relation to that case which, if that Court had not ceased to have\njurisdiction, might have been had therein, may be had in the Court to which the business of the former\nCourt is transferred by sub-section (2); but this sub-section shall not apply to cases for which provision\nis made in section 623 or section 649 of the Code of Civil Procedure1\n(14 of 1882).\n\n(5) In the case of appeals from the decrees and orders mentioned in sub-section (3) the period of\nlimitation shall be calculated in accordance with the provisions of section 15 of the Jhansi Courts\nAct, 18672\n(18 of 1867), as though this Act had not been passed.",
        "footnotes": "1.Sub-section (1) rep., by Act 1 of 1938.\n\n2. That is, the 1st April, 1891.\n\n3. “Agra” has been subs. for “North-Western Provinces” by Act 16 of 1911.",
        "query": "abv=CEN&statehandle=123456789/1362&actid=AC_CEN_5_5_00114_189020_1666335792135&sectionId=70506&sectionno=9&orderno=8&orgactid=AC_CEN_5_5_00114_189020_1666335792135"
      },
      {
        "sectionId": "70507",
        "sectionNo": "10",
        "orderNo": 9,
        "title": "Commencement of Part II.",
        "content": "This Part shall come into force on such day^1\nas the Chief\nCommissioner of Oudh may, by notification in the Official Gazette, direct.",
        "footnotes": "1. 1st January, 1891, see the North-Western Provinces and Oudh\nGazette, 1890, Pt. I, p.661.",
        "query": "abv=CEN&statehandle=123456789/1362&actid=AC_CEN_5_5_00114_189020_1666335792135&sectionId=70507&sectionno=10&orderno=9&orgactid=AC_CEN_5_5_00114_189020_1666335792135"
      },
      {
        "sectionId": "70565",
        "sectionNo": "11",
        "orderNo": 10,
        "title": "Board of Revenue of the North-Western Provinces to be the Board of Revenue of, and Chief Revenue-authority in, Oudh.",
        "content": "(1) On and from the day on which this Part comes into force\nthe Board of Revenue constituted under the North-Western Provinces Land-revenue Act, 1873^1\n(19 of 1873), shall be deemed to be also the Board of Revenue for the territories administered by the Chief Commissioner of Oudh, and shall be known and designated as the Board of Revenue of the NorthWestern Provinces and Oudh^2.\n\n(2) All references made in any enactment as amended by this Part to the Board of Revenue shall be\ndeemed, so far as they relate to Oudh, to refer to the said Board.\n\n(3) In any enactment for the time being in force in the territories administered by the Chief\nCommissioner of Oudh, in which the expression “Chief Revenue-authority” or “Chief Controlling\nRevenue-authority” is used, the expression shall, subject to the provisions of any enactment passed\nafter the said day^3\n, be construed, so far as the said territories are concerned, as referring to the Board\nof Revenue of the North-Western Provinces and Oudh^2\n.",
        "footnotes": "1. Since rep. by the U.P. Land-revenue Act,1901 (U.P. 3 of 1901), s. 2, but not so as to affect anything done under Act 19 of\n1873, see s. 3.\n\n2. Now the Board of Revenue of the U.P.\n\n3. 1st January, 1891, see the North-Western Provinces and Oudh Gazette, 1890, Pt. I, p.661.",
        "query": "abv=CEN&statehandle=123456789/1362&actid=AC_CEN_5_5_00114_189020_1666335792135&sectionId=70565&sectionno=11&orderno=10&orgactid=AC_CEN_5_5_00114_189020_1666335792135"
      },
      {
        "sectionId": "70509",
        "sectionNo": "12",
        "orderNo": 11,
        "title": "[Repealed.].",
        "content": "Rep. by the U.P. Act, 1901 (3 of 1901).",
        "footnotes": "",
        "query": "abv=CEN&statehandle=123456789/1362&actid=AC_CEN_5_5_00114_189020_1666335792135&sectionId=70509&sectionno=12&orderno=11&orgactid=AC_CEN_5_5_00114_189020_1666335792135"
      },
      {
        "sectionId": "70510",
        "sectionNo": "13",
        "orderNo": 12,
        "title": "[Repealed.].",
        "content": "Rep. by the U.P. Act, 1901 (3 of 1901).",
        "footnotes": "",
        "query": "abv=CEN&statehandle=123456789/1362&actid=AC_CEN_5_5_00114_189020_1666335792135&sectionId=70510&sectionno=13&orderno=12&orgactid=AC_CEN_5_5_00114_189020_1666335792135"
      },
      {
        "sectionId": "70511",
        "sectionNo": "14",
        "orderNo": 13,
        "title": "[Repealed.].",
        "content": "Rep. by the U.P. Act, 1901 (3 of 1901).",
        "footnotes": "",
        "query": "abv=CEN&statehandle=123456789/1362&actid=AC_CEN_5_5_00114_189020_1666335792135&sectionId=70511&sectionno=14&orderno=13&orgactid=AC_CEN_5_5_00114_189020_1666335792135"
      },
      {
        "sectionId": "70512",
        "sectionNo": "15",
        "orderNo": 14,
        "title": "[Repealed.].",
        "content": "Rep. by the U.P. Act, 1901 (3 of 1901).",
        "footnotes": "",
        "query": "abv=CEN&statehandle=123456789/1362&actid=AC_CEN_5_5_00114_189020_1666335792135&sectionId=70512&sectionno=15&orderno=14&orgactid=AC_CEN_5_5_00114_189020_1666335792135"
      },
      {
        "sectionId": "70513",
        "sectionNo": "16",
        "orderNo": 15,
        "title": "[Repealed.].",
        "content": "Rep. by the U.P. Act, 1901 (3 of 1901).",
        "footnotes": "",
        "query": "abv=CEN&statehandle=123456789/1362&actid=AC_CEN_5_5_00114_189020_1666335792135&sectionId=70513&sectionno=16&orderno=15&orgactid=AC_CEN_5_5_00114_189020_1666335792135"
      },
      {
        "sectionId": "70514",
        "sectionNo": "17",
        "orderNo": 16,
        "title": "[Repealed.].",
        "content": "Rep. by the Repealing and Amending Act, 1891 (12 of 1891)",
        "footnotes": "",
        "query": "abv=CEN&statehandle=123456789/1362&actid=AC_CEN_5_5_00114_189020_1666335792135&sectionId=70514&sectionno=17&orderno=16&orgactid=AC_CEN_5_5_00114_189020_1666335792135"
      },
      {
        "sectionId": "70515",
        "sectionNo": "18",
        "orderNo": 17,
        "title": "[Repealed.].",
        "content": "Rep. by the U.P. Act, 1901 (3 of 1901).",
        "footnotes": "",
        "query": "abv=CEN&statehandle=123456789/1362&actid=AC_CEN_5_5_00114_189020_1666335792135&sectionId=70515&sectionno=18&orderno=17&orgactid=AC_CEN_5_5_00114_189020_1666335792135"
      },
      {
        "sectionId": "70516",
        "sectionNo": "19",
        "orderNo": 18,
        "title": "[Repealed.].",
        "content": "Rep. by the U.P. Act, 1901 (3 of 1901).",
        "footnotes": "",
        "query": "abv=CEN&statehandle=123456789/1362&actid=AC_CEN_5_5_00114_189020_1666335792135&sectionId=70516&sectionno=19&orderno=18&orgactid=AC_CEN_5_5_00114_189020_1666335792135"
      },
      {
        "sectionId": "70517",
        "sectionNo": "20",
        "orderNo": 19,
        "title": "[Repealed.].",
        "content": "",
        "footnotes": "",
        "query": "abv=CEN&statehandle=123456789/1362&actid=AC_CEN_5_5_00114_189020_1666335792135&sectionId=70517&sectionno=20&orderno=19&orgactid=AC_CEN_5_5_00114_189020_1666335792135"
      },
      {
        "sectionId": "70518",
        "sectionNo": "21",
        "orderNo": 20,
        "title": "[Repealed.].",
        "content": "Rep. by the U.P. Act, 1901 (3 of 1901).",
        "footnotes": "",
        "query": "abv=CEN&statehandle=123456789/1362&actid=AC_CEN_5_5_00114_189020_1666335792135&sectionId=70518&sectionno=21&orderno=20&orgactid=AC_CEN_5_5_00114_189020_1666335792135"
      },
      {
        "sectionId": "70519",
        "sectionNo": "22",
        "orderNo": 21,
        "title": "[Repealed.].",
        "content": "Rep. by the U.P. Act, 1901 (3 of 1901).",
        "footnotes": "",
        "query": "abv=CEN&statehandle=123456789/1362&actid=AC_CEN_5_5_00114_189020_1666335792135&sectionId=70519&sectionno=22&orderno=21&orgactid=AC_CEN_5_5_00114_189020_1666335792135"
      },
      {
        "sectionId": "70520",
        "sectionNo": "23",
        "orderNo": 22,
        "title": "[Repealed.].",
        "content": "Rep. by the U.P. Act, 1901 (3 of 1901)",
        "footnotes": "",
        "query": "abv=CEN&statehandle=123456789/1362&actid=AC_CEN_5_5_00114_189020_1666335792135&sectionId=70520&sectionno=23&orderno=22&orgactid=AC_CEN_5_5_00114_189020_1666335792135"
      },
      {
        "sectionId": "70521",
        "sectionNo": "24",
        "orderNo": 23,
        "title": "[Repealed.].",
        "content": "Rep. by the U.P. Act, 1901 (3 of 1901).",
        "footnotes": "",
        "query": "abv=CEN&statehandle=123456789/1362&actid=AC_CEN_5_5_00114_189020_1666335792135&sectionId=70521&sectionno=24&orderno=23&orgactid=AC_CEN_5_5_00114_189020_1666335792135"
      },
      {
        "sectionId": "70522",
        "sectionNo": "25",
        "orderNo": 24,
        "title": "[Repealed.].",
        "content": "Rep. by the U.P. Act, 1901 (3 of 1901).",
        "footnotes": "",
        "query": "abv=CEN&statehandle=123456789/1362&actid=AC_CEN_5_5_00114_189020_1666335792135&sectionId=70522&sectionno=25&orderno=24&orgactid=AC_CEN_5_5_00114_189020_1666335792135"
      },
      {
        "sectionId": "70523",
        "sectionNo": "26",
        "orderNo": 25,
        "title": "[Repealed.].",
        "content": "Rep. by the U.P. Act, 1901 (3 of 1901).",
        "footnotes": "",
        "query": "abv=CEN&statehandle=123456789/1362&actid=AC_CEN_5_5_00114_189020_1666335792135&sectionId=70523&sectionno=26&orderno=25&orgactid=AC_CEN_5_5_00114_189020_1666335792135"
      },
      {
        "sectionId": "70524",
        "sectionNo": "27",
        "orderNo": 26,
        "title": "[Repealed.].",
        "content": "Rep. by the U.P. Act, 1901 (3 of 1901).",
        "footnotes": "",
        "query": "abv=CEN&statehandle=123456789/1362&actid=AC_CEN_5_5_00114_189020_1666335792135&sectionId=70524&sectionno=27&orderno=26&orgactid=AC_CEN_5_5_00114_189020_1666335792135"
      },
      {
        "sectionId": "70525",
        "sectionNo": "28",
        "orderNo": 27,
        "title": "[Repealed.].",
        "content": "Rep. by the U.P. Act, 1899 (3 of 1899).",
        "footnotes": "",
        "query": "abv=CEN&statehandle=123456789/1362&actid=AC_CEN_5_5_00114_189020_1666335792135&sectionId=70525&sectionno=28&orderno=27&orgactid=AC_CEN_5_5_00114_189020_1666335792135"
      },
      {
        "sectionId": "70526",
        "sectionNo": "29",
        "orderNo": 28,
        "title": "[Repealed.].",
        "content": "Rep. by the U.P. Act, 1899 (3 of 1899).",
        "footnotes": "",
        "query": "abv=CEN&statehandle=123456789/1362&actid=AC_CEN_5_5_00114_189020_1666335792135&sectionId=70526&sectionno=29&orderno=28&orgactid=AC_CEN_5_5_00114_189020_1666335792135"
      },
      {
        "sectionId": "70527",
        "sectionNo": "30",
        "orderNo": 29,
        "title": "[Repealed.].",
        "content": "Rep. by the U.P. Act, 1899 (3 of 1899).",
        "footnotes": "",
        "query": "abv=CEN&statehandle=123456789/1362&actid=AC_CEN_5_5_00114_189020_1666335792135&sectionId=70527&sectionno=30&orderno=29&orgactid=AC_CEN_5_5_00114_189020_1666335792135"
      },
      {
        "sectionId": "70528",
        "sectionNo": "31",
        "orderNo": 30,
        "title": "[Repealed.].",
        "content": "Rep. by the U.P. Act, 1899 (3 of 1899)",
        "footnotes": "",
        "query": "abv=CEN&statehandle=123456789/1362&actid=AC_CEN_5_5_00114_189020_1666335792135&sectionId=70528&sectionno=31&orderno=30&orgactid=AC_CEN_5_5_00114_189020_1666335792135"
      },
      {
        "sectionId": "70529",
        "sectionNo": "32",
        "orderNo": 31,
        "title": "[Repealed.].",
        "content": "Rep. by the U.P. Act, 1901 (3 of 1901).",
        "footnotes": "",
        "query": "abv=CEN&statehandle=123456789/1362&actid=AC_CEN_5_5_00114_189020_1666335792135&sectionId=70529&sectionno=32&orderno=31&orgactid=AC_CEN_5_5_00114_189020_1666335792135"
      },
      {
        "sectionId": "70530",
        "sectionNo": "33",
        "orderNo": 32,
        "title": "[Repealed.].",
        "content": "Rep. by the U.P. Act, 1901 (3 of 1901).",
        "footnotes": "",
        "query": "abv=CEN&statehandle=123456789/1362&actid=AC_CEN_5_5_00114_189020_1666335792135&sectionId=70530&sectionno=33&orderno=32&orgactid=AC_CEN_5_5_00114_189020_1666335792135"
      },
      {
        "sectionId": "70531",
        "sectionNo": "34",
        "orderNo": 33,
        "title": "[Repealed.].",
        "content": "Rep. by the U.P. Act ,1901 (3 of 1901)",
        "footnotes": "",
        "query": "abv=CEN&statehandle=123456789/1362&actid=AC_CEN_5_5_00114_189020_1666335792135&sectionId=70531&sectionno=34&orderno=33&orgactid=AC_CEN_5_5_00114_189020_1666335792135"
      },
      {
        "sectionId": "70532",
        "sectionNo": "35",
        "orderNo": 34,
        "title": "[Repealed.].",
        "content": "Rep. by the Repealing and Amending Act, 1891 (12 of 1891).",
        "footnotes": "",
        "query": "abv=CEN&statehandle=123456789/1362&actid=AC_CEN_5_5_00114_189020_1666335792135&sectionId=70532&sectionno=35&orderno=34&orgactid=AC_CEN_5_5_00114_189020_1666335792135"
      },
      {
        "sectionId": "70533",
        "sectionNo": "36",
        "orderNo": 35,
        "title": "[Repealed.].",
        "content": "Rep. by the U.P. Act, 1894 (5 of 1894).",
        "footnotes": "",
        "query": "abv=CEN&statehandle=123456789/1362&actid=AC_CEN_5_5_00114_189020_1666335792135&sectionId=70533&sectionno=36&orderno=35&orgactid=AC_CEN_5_5_00114_189020_1666335792135"
      },
      {
        "sectionId": "70534",
        "sectionNo": "37",
        "orderNo": 36,
        "title": "[Repealed.].",
        "content": "Rep. by the U.P. Act, 1894 (5 of 1894).",
        "footnotes": "",
        "query": "abv=CEN&statehandle=123456789/1362&actid=AC_CEN_5_5_00114_189020_1666335792135&sectionId=70534&sectionno=37&orderno=36&orgactid=AC_CEN_5_5_00114_189020_1666335792135"
      },
      {
        "sectionId": "70535",
        "sectionNo": "38",
        "orderNo": 37,
        "title": "[Repealed.].",
        "content": "Rep. by the Repealing Act, 1938 (1 of 1938).",
        "footnotes": "",
        "query": "abv=CEN&statehandle=123456789/1362&actid=AC_CEN_5_5_00114_189020_1666335792135&sectionId=70535&sectionno=38&orderno=37&orgactid=AC_CEN_5_5_00114_189020_1666335792135"
      },
      {
        "sectionId": "70536",
        "sectionNo": "39",
        "orderNo": 38,
        "title": "[Repealed.].",
        "content": "Rep. by the U.P. Act, 1925 (4 of 1925).",
        "footnotes": "",
        "query": "abv=CEN&statehandle=123456789/1362&actid=AC_CEN_5_5_00114_189020_1666335792135&sectionId=70536&sectionno=39&orderno=38&orgactid=AC_CEN_5_5_00114_189020_1666335792135"
      },
      {
        "sectionId": "70537",
        "sectionNo": "40",
        "orderNo": 39,
        "title": "[Repealed.].",
        "content": "Rep. by the U.P. Act, 1925 (4 of 1925)",
        "footnotes": "",
        "query": "abv=CEN&statehandle=123456789/1362&actid=AC_CEN_5_5_00114_189020_1666335792135&sectionId=70537&sectionno=40&orderno=39&orgactid=AC_CEN_5_5_00114_189020_1666335792135"
      },
      {
        "sectionId": "70538",
        "sectionNo": "41",
        "orderNo": 40,
        "title": "[Repealed.].",
        "content": "Rep. by the U.P. Act, 1925 (4 of 1925).",
        "footnotes": "",
        "query": "abv=CEN&statehandle=123456789/1362&actid=AC_CEN_5_5_00114_189020_1666335792135&sectionId=70538&sectionno=41&orderno=40&orgactid=AC_CEN_5_5_00114_189020_1666335792135"
      },
      {
        "sectionId": "70539",
        "sectionNo": "42",
        "orderNo": 41,
        "title": "[Repealed.].",
        "content": "Rep. by the U.P. Act, 1925 (4 of 1925).",
        "footnotes": "",
        "query": "abv=CEN&statehandle=123456789/1362&actid=AC_CEN_5_5_00114_189020_1666335792135&sectionId=70539&sectionno=42&orderno=41&orgactid=AC_CEN_5_5_00114_189020_1666335792135"
      },
      {
        "sectionId": "70540",
        "sectionNo": "43",
        "orderNo": 42,
        "title": "[Repealed.].",
        "content": "Rep. by the Repealing and Amending Act, 1891 (12 of 1891).",
        "footnotes": "",
        "query": "abv=CEN&statehandle=123456789/1362&actid=AC_CEN_5_5_00114_189020_1666335792135&sectionId=70540&sectionno=43&orderno=42&orgactid=AC_CEN_5_5_00114_189020_1666335792135"
      },
      {
        "sectionId": "70541",
        "sectionNo": "44",
        "orderNo": 43,
        "title": "[Repealed.].",
        "content": "Rep. by the Repealing Act, 1938 (1 of 1938).",
        "footnotes": "",
        "query": "abv=CEN&statehandle=123456789/1362&actid=AC_CEN_5_5_00114_189020_1666335792135&sectionId=70541&sectionno=44&orderno=43&orgactid=AC_CEN_5_5_00114_189020_1666335792135"
      },
      {
        "sectionId": "70542",
        "sectionNo": "45",
        "orderNo": 44,
        "title": "[Repealed.].",
        "content": "Rep. by the Repealing Act, 1938 (1 of 1938)",
        "footnotes": "",
        "query": "abv=CEN&statehandle=123456789/1362&actid=AC_CEN_5_5_00114_189020_1666335792135&sectionId=70542&sectionno=45&orderno=44&orgactid=AC_CEN_5_5_00114_189020_1666335792135"
      },
      {
        "sectionId": "70543",
        "sectionNo": "46",
        "orderNo": 45,
        "title": "[Repealed.].",
        "content": "Rep. by the Repealing Act, 1938 (1 of 1938).",
        "footnotes": "",
        "query": "abv=CEN&statehandle=123456789/1362&actid=AC_CEN_5_5_00114_189020_1666335792135&sectionId=70543&sectionno=46&orderno=45&orgactid=AC_CEN_5_5_00114_189020_1666335792135"
      },
      {
        "sectionId": "70544",
        "sectionNo": "47",
        "orderNo": 46,
        "title": "[Repealed.].",
        "content": "Rep. by the Repealing Act, 1938 (1 of 1938).",
        "footnotes": "",
        "query": "abv=CEN&statehandle=123456789/1362&actid=AC_CEN_5_5_00114_189020_1666335792135&sectionId=70544&sectionno=47&orderno=46&orgactid=AC_CEN_5_5_00114_189020_1666335792135"
      },
      {
        "sectionId": "70545",
        "sectionNo": "48",
        "orderNo": 47,
        "title": "[Repealed.].",
        "content": "Rep. by the Repealing and Amending Act, 1891 (12 of 1891).",
        "footnotes": "",
        "query": "abv=CEN&statehandle=123456789/1362&actid=AC_CEN_5_5_00114_189020_1666335792135&sectionId=70545&sectionno=48&orderno=47&orgactid=AC_CEN_5_5_00114_189020_1666335792135"
      },
      {
        "sectionId": "70546",
        "sectionNo": "49",
        "orderNo": 48,
        "title": "[Repealed.].",
        "content": "Rep. by the Repealing Act, 1938 (1 of 1938).",
        "footnotes": "",
        "query": "abv=CEN&statehandle=123456789/1362&actid=AC_CEN_5_5_00114_189020_1666335792135&sectionId=70546&sectionno=49&orderno=48&orgactid=AC_CEN_5_5_00114_189020_1666335792135"
      },
      {
        "sectionId": "70547",
        "sectionNo": "50",
        "orderNo": 49,
        "title": "[Repealed.].",
        "content": "Rep. by the Repealing and Amending Act, 1891 (12 of 1891).",
        "footnotes": "",
        "query": "abv=CEN&statehandle=123456789/1362&actid=AC_CEN_5_5_00114_189020_1666335792135&sectionId=70547&sectionno=50&orderno=49&orgactid=AC_CEN_5_5_00114_189020_1666335792135"
      },
      {
        "sectionId": "70548",
        "sectionNo": "51",
        "orderNo": 50,
        "title": "[Repealed.].",
        "content": "Rep. by the Repealing Act, 1938 (1 of 1938).",
        "footnotes": "",
        "query": "abv=CEN&statehandle=123456789/1362&actid=AC_CEN_5_5_00114_189020_1666335792135&sectionId=70548&sectionno=51&orderno=50&orgactid=AC_CEN_5_5_00114_189020_1666335792135"
      },
      {
        "sectionId": "70549",
        "sectionNo": "52",
        "orderNo": 51,
        "title": "[Repealed.].",
        "content": "Rep. by the Repealing Act, 1938 (1 of 1938).",
        "footnotes": "",
        "query": "abv=CEN&statehandle=123456789/1362&actid=AC_CEN_5_5_00114_189020_1666335792135&sectionId=70549&sectionno=52&orderno=51&orgactid=AC_CEN_5_5_00114_189020_1666335792135"
      },
      {
        "sectionId": "70550",
        "sectionNo": "53",
        "orderNo": 52,
        "title": "[Repealed.].",
        "content": "Rep. by the Repealing Act, 1938 (1 of 1938).",
        "footnotes": "",
        "query": "abv=CEN&statehandle=123456789/1362&actid=AC_CEN_5_5_00114_189020_1666335792135&sectionId=70550&sectionno=53&orderno=52&orgactid=AC_CEN_5_5_00114_189020_1666335792135"
      },
      {
        "sectionId": "70551",
        "sectionNo": "54",
        "orderNo": 53,
        "title": "Pending appeals.",
        "content": "All appeals pending when this Part comes into force^1\nfrom decrees or\norders passed under the same Act shall be disposed of\nas if this Act had not been passed:\n\nProvided that the ^2[\nState Government] may, by order, transfer to the District Judge any appeals then\npending before the Commissioner or Collector in cases in which the appeal will, under the Oudh Rent\nAct, 1886, (22 of 1886) as amended by this Part, lie to the District Judge.",
        "footnotes": "1. That is, the 1st January, 1891.\n\n2. Subs. by the A.O. 1937 for “Chief Commissioner”",
        "query": "abv=CEN&statehandle=123456789/1362&actid=AC_CEN_5_5_00114_189020_1666335792135&sectionId=70551&sectionno=54&orderno=53&orgactid=AC_CEN_5_5_00114_189020_1666335792135"
      },
      {
        "sectionId": "70552",
        "sectionNo": "55",
        "orderNo": 54,
        "title": "[Repealed.].",
        "content": "Rep. by the Repealing Act, 1938 (1 of 1938).",
        "footnotes": "",
        "query": "abv=CEN&statehandle=123456789/1362&actid=AC_CEN_5_5_00114_189020_1666335792135&sectionId=70552&sectionno=55&orderno=54&orgactid=AC_CEN_5_5_00114_189020_1666335792135"
      },
      {
        "sectionId": "70553",
        "sectionNo": "56",
        "orderNo": 55,
        "title": "[Repealed.].",
        "content": "Rep. by the Repealing and Amending Act, 1891 (12 of 1891).",
        "footnotes": "",
        "query": "abv=CEN&statehandle=123456789/1362&actid=AC_CEN_5_5_00114_189020_1666335792135&sectionId=70553&sectionno=56&orderno=55&orgactid=AC_CEN_5_5_00114_189020_1666335792135"
      },
      {
        "sectionId": "70554",
        "sectionNo": "57",
        "orderNo": 56,
        "title": "[Repealed.].",
        "content": "Rep. by the Repealing Act, 1938 (1 of 1938).",
        "footnotes": "",
        "query": "abv=CEN&statehandle=123456789/1362&actid=AC_CEN_5_5_00114_189020_1666335792135&sectionId=70554&sectionno=57&orderno=56&orgactid=AC_CEN_5_5_00114_189020_1666335792135"
      },
      {
        "sectionId": "70555",
        "sectionNo": "58",
        "orderNo": 57,
        "title": "[Repealed.].",
        "content": "Rep. by the Repealing Act, 1938 (1 of 1938).",
        "footnotes": "",
        "query": "abv=CEN&statehandle=123456789/1362&actid=AC_CEN_5_5_00114_189020_1666335792135&sectionId=70555&sectionno=58&orderno=57&orgactid=AC_CEN_5_5_00114_189020_1666335792135"
      },
      {
        "sectionId": "70556",
        "sectionNo": "59",
        "orderNo": 58,
        "title": "[Repealed.].",
        "content": "Rep. by the Repealing Act, 1938 (1 of 1938)",
        "footnotes": "",
        "query": "abv=CEN&statehandle=123456789/1362&actid=AC_CEN_5_5_00114_189020_1666335792135&sectionId=70556&sectionno=59&orderno=58&orgactid=AC_CEN_5_5_00114_189020_1666335792135"
      },
      {
        "sectionId": "70557",
        "sectionNo": "60",
        "orderNo": 59,
        "title": "[Repealed.].",
        "content": "Rep. by the Repealing Act, 1938 (1 of 1938).",
        "footnotes": "",
        "query": "abv=CEN&statehandle=123456789/1362&actid=AC_CEN_5_5_00114_189020_1666335792135&sectionId=70557&sectionno=60&orderno=59&orgactid=AC_CEN_5_5_00114_189020_1666335792135"
      },
      {
        "sectionId": "70558",
        "sectionNo": "61",
        "orderNo": 60,
        "title": "[Repealed.].",
        "content": "Rep. by the Repealing Act, 1938 (1 of 1938).",
        "footnotes": "",
        "query": "abv=CEN&statehandle=123456789/1362&actid=AC_CEN_5_5_00114_189020_1666335792135&sectionId=70558&sectionno=61&orderno=60&orgactid=AC_CEN_5_5_00114_189020_1666335792135"
      },
      {
        "sectionId": "70559",
        "sectionNo": "62",
        "orderNo": 61,
        "title": "Commencement of Part III.",
        "content": "This part shall come into force on such day3\nas the Lieutenant\nGovernor of the North-Western Provinces and Chief Commissioner of Oudh may, by notification in the\nOfficial Gazette, direct.",
        "footnotes": "",
        "query": "abv=CEN&statehandle=123456789/1362&actid=AC_CEN_5_5_00114_189020_1666335792135&sectionId=70559&sectionno=62&orderno=61&orgactid=AC_CEN_5_5_00114_189020_1666335792135"
      },
      {
        "sectionId": "70560",
        "sectionNo": "63",
        "orderNo": 62,
        "title": "Place where the Board may sit.",
        "content": "(1) Notwithstanding anything ^1\n*** in section 128 of the\nOudh Rent Act, 1886 (22 of 1886), the Board of Revenue of the North-Western Provinces and Oudh\nshall, for the disposal of cases under those Acts, sit in such place or places in the North-Western\nProvinces or Oudh as ^2[\nthe State Government] may, by notification in the Official Gazette,6\nappoint in\nrespect to cases under either of those Acts.\n\n(2) For the disposal of cases other than those referred to in sub-section (1) the said Board may,\nsubject to the orders of ^2[the State Government], sit in any place in the North-Western Provinces or\nOudh that the Board thinks fit.",
        "footnotes": "1. Section 63, so far as it relates to Act 12 of 1881, that is the words “in s. 152 of the North-Western Provinces Rent\nAct, 1881, or” were rep. by the Agra Tenancy Act, 1901 (U.P. 2 of 1901).\n\n2.Subs. by the A.O. 1937 for “the said Lieutenant-Governor and Chief Commissioner”",
        "query": "abv=CEN&statehandle=123456789/1362&actid=AC_CEN_5_5_00114_189020_1666335792135&sectionId=70560&sectionno=63&orderno=62&orgactid=AC_CEN_5_5_00114_189020_1666335792135"
      },
      {
        "sectionId": "70561",
        "sectionNo": "64",
        "orderNo": 63,
        "title": "[Repealed.].",
        "content": "[Amendment of section 4, Act 19 of 1873.] Rep. by the United Provinces Land-revenue\nAct, 1901 (U.P. Act 3 of 1901).",
        "footnotes": "",
        "query": "abv=CEN&statehandle=123456789/1362&actid=AC_CEN_5_5_00114_189020_1666335792135&sectionId=70561&sectionno=64&orderno=63&orgactid=AC_CEN_5_5_00114_189020_1666335792135"
      }
    ],
    "hindiTitle": "पश्‍चिमोत्तर प्रान्‍त और अवध अधिनियम, 1890",
    "actYear": "1890",
    "ministry": "Ministry of Home Affairs",
    "department": "Department of States",
    "longTitle": "An Act to provide for the better administration of the North-Western Provinces and Oudh and to amend certain enactments in force in those Provinces and in Oudh.",
    "enforcementDate": "16-10-1890"
  }
}
